{
  "g7-english-1": {
    "id": "g7-english-1",
    "topicId": "g7-english",
    "question": "Articles: a / an / the\nPRACTICE\nI. Choose the word whose underlined part is pronounced differently from the others.",
    "choices": [
      "PHONETICS"
    ],
    "answer": 0,
    "steps": [
      {
        "text": "Dựa vào kiến thức đã học để trả lời.",
        "highlight": null
      }
    ],
    "images": []
  },
  "g7-english-2": {
    "id": "g7-english-2",
    "topicId": "g7-english",
    "question": "A. year",
    "choices": [
      "wear",
      "appear",
      "hear"
    ],
    "answer": 0,
    "steps": [
      {
        "text": "Dựa vào kiến thức đã học để trả lời.",
        "highlight": null
      }
    ],
    "images": []
  },
  "g7-english-3": {
    "id": "g7-english-3",
    "topicId": "g7-english",
    "question": "A. natural",
    "choices": [
      "poverty",
      "question",
      "future"
    ],
    "answer": 0,
    "steps": [
      {
        "text": "Dựa vào kiến thức đã học để trả lời.",
        "highlight": null
      }
    ],
    "images": []
  },
  "g7-english-4": {
    "id": "g7-english-4",
    "topicId": "g7-english",
    "question": "A. transport",
    "choices": [
      "passenger",
      "station",
      "traffic"
    ],
    "answer": 0,
    "steps": [
      {
        "text": "Dựa vào kiến thức đã học để trả lời.",
        "highlight": null
      }
    ],
    "images": []
  },
  "g7-english-5": {
    "id": "g7-english-5",
    "topicId": "g7-english",
    "question": "A. limit",
    "choices": [
      "line",
      "light",
      "like"
    ],
    "answer": 0,
    "steps": [
      {
        "text": "Dựa vào kiến thức đã học để trả lời.",
        "highlight": null
      }
    ],
    "images": []
  },
  "g7-english-6": {
    "id": "g7-english-6",
    "topicId": "g7-english",
    "question": "A. deer",
    "choices": [
      "meet",
      "atmosphere",
      "volunteer"
    ],
    "answer": 0,
    "steps": [
      {
        "text": "Dựa vào kiến thức đã học để trả lời.",
        "highlight": null
      }
    ],
    "images": []
  },
  "g7-english-7": {
    "id": "g7-english-7",
    "topicId": "g7-english",
    "question": "A. painted\nII. Choose the word that has the main stress placed differently from the others.",
    "choices": [
      "parked",
      "watched",
      "stopped"
    ],
    "answer": 0,
    "steps": [
      {
        "text": "Dựa vào kiến thức đã học để trả lời.",
        "highlight": null
      }
    ],
    "images": []
  },
  "g7-english-8": {
    "id": "g7-english-8",
    "topicId": "g7-english",
    "question": "A. turkey",
    "choices": [
      "boring",
      "joyful",
      "donate"
    ],
    "answer": 0,
    "steps": [
      {
        "text": "Dựa vào kiến thức đã học để trả lời.",
        "highlight": null
      }
    ],
    "images": []
  },
  "g7-english-9": {
    "id": "g7-english-9",
    "topicId": "g7-english",
    "question": "A. easily",
    "choices": [
      "beautiful",
      "expensive",
      "energy"
    ],
    "answer": 0,
    "steps": [
      {
        "text": "Dựa vào kiến thức đã học để trả lời.",
        "highlight": null
      }
    ],
    "images": []
  },
  "g7-english-10": {
    "id": "g7-english-10",
    "topicId": "g7-english",
    "question": "A. costumes",
    "choices": [
      "enjoy",
      "begin",
      "appear"
    ],
    "answer": 0,
    "steps": [
      {
        "text": "Dựa vào kiến thức đã học để trả lời.",
        "highlight": null
      }
    ],
    "images": []
  },
  "g7-english-11": {
    "id": "g7-english-11",
    "topicId": "g7-english",
    "question": "A. government",
    "choices": [
      "travelling",
      "dangerous",
      "polluting"
    ],
    "answer": 0,
    "steps": [
      {
        "text": "Dựa vào kiến thức đã học để trả lời.",
        "highlight": null
      }
    ],
    "images": []
  },
  "g7-english-12": {
    "id": "g7-english-12",
    "topicId": "g7-english",
    "question": "A. violent\nI. Choose the best answer A, B, C or D to complete the sentence.",
    "choices": [
      "decorate",
      "comedy",
      "director",
      "GRAMMAR & VOCABULARY"
    ],
    "answer": 0,
    "steps": [
      {
        "text": "Dựa vào kiến thức đã học để trả lời.",
        "highlight": null
      }
    ],
    "images": []
  },
  "g7-english-13": {
    "id": "g7-english-13",
    "topicId": "g7-english",
    "question": "Coal is a(n) __________ energy source.",
    "choices": [
      "renewable",
      "non-renewable",
      "expensive",
      "good for the environment"
    ],
    "answer": 0,
    "steps": [
      {
        "text": "Dựa vào kiến thức đã học để trả lời.",
        "highlight": null
      }
    ],
    "images": []
  },
  "g7-english-14": {
    "id": "g7-english-14",
    "topicId": "g7-english",
    "question": "Cyclists need to obey the traffic __________ by not carrying more than one passenger.",
    "choices": [
      "rules",
      "jams",
      "lights",
      "All are correct"
    ],
    "answer": 0,
    "steps": [
      {
        "text": "Dựa vào kiến thức đã học để trả lời.",
        "highlight": null
      }
    ],
    "images": []
  },
  "g7-english-15": {
    "id": "g7-english-15",
    "topicId": "g7-english",
    "question": "Several governments try to\nthe use of fossil fuels.",
    "choices": [
      "reduce",
      "increase",
      "waste",
      "save"
    ],
    "answer": 0,
    "steps": [
      {
        "text": "Dựa vào kiến thức đã học để trả lời.",
        "highlight": null
      }
    ],
    "images": []
  },
  "g7-english-16": {
    "id": "g7-english-16",
    "topicId": "g7-english",
    "question": "A teleporter is __________, so it doesn't cause pollution.",
    "choices": [
      "limited",
      "fast",
      "available",
      "eco-friendly"
    ],
    "answer": 0,
    "steps": [
      {
        "text": "Dựa vào kiến thức đã học để trả lời.",
        "highlight": null
      }
    ],
    "images": []
  },
  "g7-english-17": {
    "id": "g7-english-17",
    "topicId": "g7-english",
    "question": "A solowheel runs __________ electricity, so it is safe for the environment.",
    "choices": [
      "out",
      "in",
      "on",
      "by"
    ],
    "answer": 0,
    "steps": [
      {
        "text": "Dựa vào kiến thức đã học để trả lời.",
        "highlight": null
      }
    ],
    "images": []
  },
  "g7-english-18": {
    "id": "g7-english-18",
    "topicId": "g7-english",
    "question": "I have ____ list of countries and territories where English is ____ official language.",
    "choices": [
      "the - a",
      "a - an",
      "a - the",
      "an – an"
    ],
    "answer": 0,
    "steps": [
      {
        "text": "Dựa vào kiến thức đã học để trả lời.",
        "highlight": null
      }
    ],
    "images": []
  },
  "g7-english-19": {
    "id": "g7-english-19",
    "topicId": "g7-english",
    "question": "They expect zero-emission fuel cell buses to become a ______ of transport.",
    "choices": [
      "means",
      "measure",
      "instrument",
      "channel"
    ],
    "answer": 0,
    "steps": [
      {
        "text": "Dựa vào kiến thức đã học để trả lời.",
        "highlight": null
      }
    ],
    "images": []
  },
  "g7-english-20": {
    "id": "g7-english-20",
    "topicId": "g7-english",
    "question": "He is driving his car too fast, but he is not wearing his……………..",
    "choices": [
      "seatbelt",
      "helmet",
      "hat",
      "coat"
    ],
    "answer": 0,
    "steps": [
      {
        "text": "Dựa vào kiến thức đã học để trả lời.",
        "highlight": null
      }
    ],
    "images": []
  },
  "g7-english-21": {
    "id": "g7-english-21",
    "topicId": "g7-english",
    "question": "Jim wanted to ______ the boat alone, but his parents didn't agree.",
    "choices": [
      "let",
      "travel",
      "get",
      "sail"
    ],
    "answer": 0,
    "steps": [
      {
        "text": "Dựa vào kiến thức đã học để trả lời.",
        "highlight": null
      }
    ],
    "images": []
  },
  "g7-english-22": {
    "id": "g7-english-22",
    "topicId": "g7-english",
    "question": "Your bike is a normal one, but ________ is a sports bike.",
    "choices": [
      "she",
      "her",
      "herself",
      "hers"
    ],
    "answer": 0,
    "steps": [
      {
        "text": "Dựa vào kiến thức đã học để trả lời.",
        "highlight": null
      }
    ],
    "images": []
  },
  "g7-english-23": {
    "id": "g7-english-23",
    "topicId": "g7-english",
    "question": "Children should avoid ______ foods such as hamburger and snacks.",
    "choices": [
      "unhealthy",
      "nutritious",
      "uncooked",
      "fresh"
    ],
    "answer": 0,
    "steps": [
      {
        "text": "Dựa vào kiến thức đã học để trả lời.",
        "highlight": null
      }
    ],
    "images": []
  },
  "g7-english-24": {
    "id": "g7-english-24",
    "topicId": "g7-english",
    "question": "Look! The boys ___ football in the park.",
    "choices": [
      "play",
      "are playing",
      "played",
      "have played"
    ],
    "answer": 0,
    "steps": [
      {
        "text": "Dựa vào kiến thức đã học để trả lời.",
        "highlight": null
      }
    ],
    "images": []
  },
  "g7-english-25": {
    "id": "g7-english-25",
    "topicId": "g7-english",
    "question": "- How about going to the cinema tonight? - ____________",
    "choices": [
      "No, thanks.",
      "It was a big disappointment.",
      "That’s too bad.",
      "That’s a great idea!"
    ],
    "answer": 0,
    "steps": [
      {
        "text": "Dựa vào kiến thức đã học để trả lời.",
        "highlight": null
      }
    ],
    "images": []
  },
  "g7-english-26": {
    "id": "g7-english-26",
    "topicId": "g7-english",
    "question": "_______ rulers are here. _______  are there.",
    "choices": [
      "Theirs – Ours",
      "Their – Our",
      "Theirs – Our",
      "Their – Ours"
    ],
    "answer": 0,
    "steps": [
      {
        "text": "Dựa vào kiến thức đã học để trả lời.",
        "highlight": null
      }
    ],
    "images": []
  },
  "g7-english-27": {
    "id": "g7-english-27",
    "topicId": "g7-english",
    "question": "Recycling means to reuse something. The more we ______, the less energy is needed.",
    "choices": [
      "recycle",
      "build",
      "repair",
      "reuse"
    ],
    "answer": 0,
    "steps": [
      {
        "text": "Dựa vào kiến thức đã học để trả lời.",
        "highlight": null
      }
    ],
    "images": []
  },
  "g7-english-28": {
    "id": "g7-english-28",
    "topicId": "g7-english",
    "question": "______ is it from your house to the nearest bus stop? – \"About 50 meters.\"",
    "choices": [
      "How far",
      "How long",
      "How often",
      "How much"
    ],
    "answer": 0,
    "steps": [
      {
        "text": "Dựa vào kiến thức đã học để trả lời.",
        "highlight": null
      }
    ],
    "images": []
  },
  "g7-english-29": {
    "id": "g7-english-29",
    "topicId": "g7-english",
    "question": "An: Do you think we will travel by flying car in the future?\nBen: ______",
    "choices": [
      "We certainly will.",
      "Wow... I didn't know that",
      "Amazing",
      "Sounds great!"
    ],
    "answer": 0,
    "steps": [
      {
        "text": "Dựa vào kiến thức đã học để trả lời.",
        "highlight": null
      }
    ],
    "images": []
  },
  "g7-english-30": {
    "id": "g7-english-30",
    "topicId": "g7-english",
    "question": "Peter goes to school ______ foot everyday.",
    "choices": [
      "on",
      "by",
      "in",
      "over"
    ],
    "answer": 0,
    "steps": [
      {
        "text": "Dựa vào kiến thức đã học để trả lời.",
        "highlight": null
      }
    ],
    "images": []
  },
  "g7-english-31": {
    "id": "g7-english-31",
    "topicId": "g7-english",
    "question": "We couldn't stop laughing when seeing this ______.",
    "choices": [
      "horror film",
      "comedy",
      "fantasy",
      "action film"
    ],
    "answer": 0,
    "steps": [
      {
        "text": "Dựa vào kiến thức đã học để trả lời.",
        "highlight": null
      }
    ],
    "images": []
  },
  "g7-english-32": {
    "id": "g7-english-32",
    "topicId": "g7-english",
    "question": "The film is too ______ with a lot of fighting and killing scene.",
    "choices": [
      "funny",
      "violent",
      "interesting",
      "romantic"
    ],
    "answer": 0,
    "steps": [
      {
        "text": "Dựa vào kiến thức đã học để trả lời.",
        "highlight": null
      }
    ],
    "images": []
  },
  "g7-english-33": {
    "id": "g7-english-33",
    "topicId": "g7-english",
    "question": "The fans of the film filled the cinemas ______ the show time was inconvenient.",
    "choices": [
      "though",
      "so",
      "however",
      "and"
    ],
    "answer": 0,
    "steps": [
      {
        "text": "Dựa vào kiến thức đã học để trả lời.",
        "highlight": null
      }
    ],
    "images": []
  },
  "g7-english-34": {
    "id": "g7-english-34",
    "topicId": "g7-english",
    "question": "Nancy is on the way and she ______ in about half an hour.",
    "choices": [
      "arrives",
      "arrived",
      "are arriving",
      "will arrive"
    ],
    "answer": 0,
    "steps": [
      {
        "text": "Dựa vào kiến thức đã học để trả lời.",
        "highlight": null
      }
    ],
    "images": []
  },
  "g7-english-35": {
    "id": "g7-english-35",
    "topicId": "g7-english",
    "question": "There is ______ area on Planet Mars which NASA has named Glasgow.",
    "choices": [
      "a",
      "an",
      "the",
      "Ø"
    ],
    "answer": 0,
    "steps": [
      {
        "text": "Dựa vào kiến thức đã học để trả lời.",
        "highlight": null
      }
    ],
    "images": []
  },
  "g7-english-36": {
    "id": "g7-english-36",
    "topicId": "g7-english",
    "question": "Yesterday you probably brought my book home instead of ______.",
    "choices": [
      "yours",
      "your",
      "your book",
      "mine"
    ],
    "answer": 0,
    "steps": [
      {
        "text": "Dựa vào kiến thức đã học để trả lời.",
        "highlight": null
      }
    ],
    "images": []
  },
  "g7-english-37": {
    "id": "g7-english-37",
    "topicId": "g7-english",
    "question": "Angelina and Robert ______ to each other right now.",
    "choices": [
      "don't talk",
      "aren't talking",
      "won't talk",
      "didn't talk"
    ],
    "answer": 0,
    "steps": [
      {
        "text": "Dựa vào kiến thức đã học để trả lời.",
        "highlight": null
      }
    ],
    "images": []
  },
  "g7-english-38": {
    "id": "g7-english-38",
    "topicId": "g7-english",
    "question": "At present, my city ______a station for skyTrans.",
    "choices": [
      "is building",
      "will build",
      "build",
      "built"
    ],
    "answer": 0,
    "steps": [
      {
        "text": "Dựa vào kiến thức đã học để trả lời.",
        "highlight": null
      }
    ],
    "images": []
  },
  "g7-english-39": {
    "id": "g7-english-39",
    "topicId": "g7-english",
    "question": "_________ is a type of vehicle that can take off, fly, and land like an airplane but can also drive\non roads.",
    "choices": [
      "Hyperloop",
      "Teleporter",
      "Flying car",
      "Bullet train"
    ],
    "answer": 0,
    "steps": [
      {
        "text": "Dựa vào kiến thức đã học để trả lời.",
        "highlight": null
      }
    ],
    "images": []
  },
  "g7-english-40": {
    "id": "g7-english-40",
    "topicId": "g7-english",
    "question": "We _______ probably travel to the Moon in twenty years.",
    "choices": [
      "do",
      "did",
      "are",
      "will"
    ],
    "answer": 0,
    "steps": [
      {
        "text": "Dựa vào kiến thức đã học để trả lời.",
        "highlight": null
      }
    ],
    "images": []
  },
  "g7-english-41": {
    "id": "g7-english-41",
    "topicId": "g7-english",
    "question": "There ______ over 10 million sheep but just 3 million people in Wales.",
    "choices": [
      "was",
      "were",
      "is",
      "are"
    ],
    "answer": 0,
    "steps": [
      {
        "text": "Dựa vào kiến thức đã học để trả lời.",
        "highlight": null
      }
    ],
    "images": []
  },
  "g7-english-42": {
    "id": "g7-english-42",
    "topicId": "g7-english",
    "question": "A non- renewable source of energy can be used to power machinery, but it also _________the\nenvironment.",
    "choices": [
      "cleans",
      "pollutes",
      "helps",
      "protects"
    ],
    "answer": 0,
    "steps": [
      {
        "text": "Dựa vào kiến thức đã học để trả lời.",
        "highlight": null
      }
    ],
    "images": []
  },
  "g7-english-43": {
    "id": "g7-english-43",
    "topicId": "g7-english",
    "question": "Canada and ______ USA share ______ longest international border in ______ world.",
    "choices": [
      "the - the - a",
      "the - a - the",
      "the - the - the",
      "the - the - a"
    ],
    "answer": 0,
    "steps": [
      {
        "text": "Dựa vào kiến thức đã học để trả lời.",
        "highlight": null
      }
    ],
    "images": []
  },
  "g7-english-44": {
    "id": "g7-english-44",
    "topicId": "g7-english",
    "question": "The city has a ten-minute long ______ display on New Year's Eve.",
    "choices": [
      "fireworks",
      "costumes",
      "feast",
      "parade"
    ],
    "answer": 0,
    "steps": [
      {
        "text": "Dựa vào kiến thức đã học để trả lời.",
        "highlight": null
      }
    ],
    "images": []
  },
  "g7-english-45": {
    "id": "g7-english-45",
    "topicId": "g7-english",
    "question": "______ you buy a birthday present for Brian next Sunday?",
    "choices": [
      "Are",
      "Will",
      "Did",
      "Do"
    ],
    "answer": 0,
    "steps": [
      {
        "text": "Dựa vào kiến thức đã học để trả lời.",
        "highlight": null
      }
    ],
    "images": []
  },
  "g7-english-46": {
    "id": "g7-english-46",
    "topicId": "g7-english",
    "question": "People need to find some other means of ______ to deal with traffic jams.",
    "choices": [
      "transport",
      "vehicle",
      "travelling",
      "living"
    ],
    "answer": 0,
    "steps": [
      {
        "text": "Dựa vào kiến thức đã học để trả lời.",
        "highlight": null
      }
    ],
    "images": []
  },
  "g7-english-47": {
    "id": "g7-english-47",
    "topicId": "g7-english",
    "question": "The play was so boring. ____________, Lan saw it from beginning to end.",
    "choices": [
      "Therefore",
      "Despite",
      "However",
      "Although"
    ],
    "answer": 0,
    "steps": [
      {
        "text": "Dựa vào kiến thức đã học để trả lời.",
        "highlight": null
      }
    ],
    "images": []
  },
  "g7-english-48": {
    "id": "g7-english-48",
    "topicId": "g7-english",
    "question": "Dogs love to play with a ball, and it is a favourite activity of ______.",
    "choices": [
      "their",
      "theirs",
      "its",
      "it"
    ],
    "answer": 0,
    "steps": [
      {
        "text": "Dựa vào kiến thức đã học để trả lời.",
        "highlight": null
      }
    ],
    "images": []
  },
  "g7-english-49": {
    "id": "g7-english-49",
    "topicId": "g7-english",
    "question": "Because vehicles using fossil fuels cause pollution, scientists want to find a cheaper and\n___________ replacement.",
    "choices": [
      "inconvenient",
      "dangerous",
      "polluted",
      "eco-friendly"
    ],
    "answer": 0,
    "steps": [
      {
        "text": "Dựa vào kiến thức đã học để trả lời.",
        "highlight": null
      }
    ],
    "images": []
  },
  "g7-english-50": {
    "id": "g7-english-50",
    "topicId": "g7-english",
    "question": "______ easy for them to build another metro system?",
    "choices": [
      "Be will it",
      "Be it will",
      "It will be",
      "Will it be"
    ],
    "answer": 0,
    "steps": [
      {
        "text": "Dựa vào kiến thức đã học để trả lời.",
        "highlight": null
      }
    ],
    "images": []
  },
  "g7-english-51": {
    "id": "g7-english-51",
    "topicId": "g7-english",
    "question": "Your idea is good, but not as good as ______.",
    "choices": [
      "ours",
      "our",
      "we",
      "us"
    ],
    "answer": 0,
    "steps": [
      {
        "text": "Dựa vào kiến thức đã học để trả lời.",
        "highlight": null
      }
    ],
    "images": []
  },
  "g7-english-52": {
    "id": "g7-english-52",
    "topicId": "g7-english",
    "question": "Do you think that ______ pleasant to ride a solowheel in bad weather?",
    "choices": [
      "it won't be",
      "will it be not",
      "will it not be",
      "won't it be"
    ],
    "answer": 0,
    "steps": [
      {
        "text": "Dựa vào kiến thức đã học để trả lời.",
        "highlight": null
      }
    ],
    "images": []
  },
  "g7-english-53": {
    "id": "g7-english-53",
    "topicId": "g7-english",
    "question": "I think future planes ______ like the UFOs.",
    "choices": [
      "look",
      "looks",
      "will look",
      "are looking"
    ],
    "answer": 0,
    "steps": [
      {
        "text": "Dựa vào kiến thức đã học để trả lời.",
        "highlight": null
      }
    ],
    "images": []
  },
  "g7-english-54": {
    "id": "g7-english-54",
    "topicId": "g7-english",
    "question": "John talks to Ann, and he suggests going to the cinema.\nJohn: “Would you like to go to the cinema this weekend?”  - Ann: “ ____________________”",
    "choices": [
      "I don’t care.",
      "Ok. You did it!",
      "Great! I can’t wait.",
      "Sorry. I don’t like."
    ],
    "answer": 0,
    "steps": [
      {
        "text": "Dựa vào kiến thức đã học để trả lời.",
        "highlight": null
      }
    ],
    "images": []
  },
  "g7-english-55": {
    "id": "g7-english-55",
    "topicId": "g7-english",
    "question": "The distance between France and England is ______ 34 kilometers.",
    "choices": [
      "of",
      "about",
      "for",
      "in"
    ],
    "answer": 0,
    "steps": [
      {
        "text": "Dựa vào kiến thức đã học để trả lời.",
        "highlight": null
      }
    ],
    "images": []
  },
  "g7-english-56": {
    "id": "g7-english-56",
    "topicId": "g7-english",
    "question": "_________ is anyone who uses a road, such as a pedestrian or motorist.",
    "choices": [
      "Passenger",
      "Driver",
      "Road user",
      "Cyclist"
    ],
    "answer": 0,
    "steps": [
      {
        "text": "Dựa vào kiến thức đã học để trả lời.",
        "highlight": null
      }
    ],
    "images": []
  },
  "g7-english-57": {
    "id": "g7-english-57",
    "topicId": "g7-english",
    "question": "You __________ bring fireworks to the festival, as it is strictly prohibited.\nII. Mark the letter A, B, C or D on your answer sheet to indicate the correct answer to each of the\nfollowing questions.\n*  46. Our family planned to watch a movie together last night. We were looking forward to it, but\n______.\na. We decided to tell stories instead.\nb. The power went out just before the movie started\nc. Everyone was disappointed because we couldn't watch the movie.",
    "choices": [
      "should",
      "must",
      "shouldn't",
      "mustn’t",
      "a-c-b",
      "c-a-b",
      "b-a-c",
      "a-b-c"
    ],
    "answer": 0,
    "steps": [
      {
        "text": "Dựa vào kiến thức đã học để trả lời.",
        "highlight": null
      }
    ],
    "images": []
  },
  "g7-english-58": {
    "id": "g7-english-58",
    "topicId": "g7-english",
    "question": "Choose the sentence that can end the text in question 46.\n* 48.  A local high school recently introduced a new computer course. It is popular among students.\n_____.\na. The course teaches students about coding and digital design.\nb. Many students have signed up for the course\nc. The school added the course to prepare students for future jobs in technology.",
    "choices": [
      "Finally, the power came back and we watched the movie",
      "We spent the evening telling stories and had a great time",
      "The power never came back, so we all went to bed early.",
      "The movie was postponed to another day.",
      "a-c-b",
      "c-a-b",
      "b-a-c",
      "c-b-a"
    ],
    "answer": 0,
    "steps": [
      {
        "text": "Dựa vào kiến thức đã học để trả lời.",
        "highlight": null
      }
    ],
    "images": []
  },
  "g7-english-59": {
    "id": "g7-english-59",
    "topicId": "g7-english",
    "question": "Choose the sentence that can end the text (in Question 48) most suitably.\nIII. Mark the letter A, B, C, or D on your answer sheet to indicate the correct option that best fits\neach of the numbered blanks\nThere is now increasing concern about the world’s energy (50)_________, particularly about those\ninvolving fossil (51) _________. In less (52)_________ a hundred years we shall probably use up all\nthe present energy of oil and gas. The world’s coal reserves should last longer, (53)_______ once used,\nthese cannot be (54)________. It is important, therefore, that we should develop such alternative\nsources of energy as solar energy as (55)________ as water and wind power, classed as renewable\nenergy.",
    "choices": [
      "The course has received good feedback from students and teachers",
      "Some students have started working on their tech projects",
      "The school is considering adding more technology-related courses",
      "There were some issues with the course schedule at first."
    ],
    "answer": 0,
    "steps": [
      {
        "text": "Dựa vào kiến thức đã học để trả lời.",
        "highlight": null
      }
    ],
    "images": [
      "/images/g7_exams/img_b0af3dfe.jpeg"
    ]
  },
  "g7-english-60": {
    "id": "g7-english-60",
    "topicId": "g7-english",
    "question": "A. possessions",
    "choices": [
      "resources",
      "goods",
      "materials"
    ],
    "answer": 0,
    "steps": [
      {
        "text": "Dựa vào kiến thức đã học để trả lời.",
        "highlight": null
      }
    ],
    "images": []
  },
  "g7-english-61": {
    "id": "g7-english-61",
    "topicId": "g7-english",
    "question": "A. fuels",
    "choices": [
      "powers",
      "forms",
      "energies"
    ],
    "answer": 0,
    "steps": [
      {
        "text": "Dựa vào kiến thức đã học để trả lời.",
        "highlight": null
      }
    ],
    "images": []
  },
  "g7-english-62": {
    "id": "g7-english-62",
    "topicId": "g7-english",
    "question": "A. in",
    "choices": [
      "more",
      "of",
      "than"
    ],
    "answer": 0,
    "steps": [
      {
        "text": "Dựa vào kiến thức đã học để trả lời.",
        "highlight": null
      }
    ],
    "images": []
  },
  "g7-english-63": {
    "id": "g7-english-63",
    "topicId": "g7-english",
    "question": "A. although",
    "choices": [
      "but",
      "so",
      "and"
    ],
    "answer": 0,
    "steps": [
      {
        "text": "Dựa vào kiến thức đã học để trả lời.",
        "highlight": null
      }
    ],
    "images": []
  },
  "g7-english-64": {
    "id": "g7-english-64",
    "topicId": "g7-english",
    "question": "A. updated",
    "choices": [
      "repeated",
      "renewed",
      "produced"
    ],
    "answer": 0,
    "steps": [
      {
        "text": "Dựa vào kiến thức đã học để trả lời.",
        "highlight": null
      }
    ],
    "images": [
      "/images/g7_exams/img_b8859909.jpeg"
    ]
  },
  "g7-english-65": {
    "id": "g7-english-65",
    "topicId": "g7-english",
    "question": "A. good\nIV. Read the following sign or notice and mark the letter A, B, C or D on your answer sheet to\nindicate the correct answer to each of the following questions.",
    "choices": [
      "well",
      "fast",
      "soon"
    ],
    "answer": 0,
    "steps": [
      {
        "text": "Dựa vào kiến thức đã học để trả lời.",
        "highlight": null
      }
    ],
    "images": []
  },
  "g7-english-66": {
    "id": "g7-english-66",
    "topicId": "g7-english",
    "question": "What does this sign mean? _______",
    "choices": [
      "You mustn’t wear shoes into this place.",
      "You can wear shoes into this place.",
      "You have to take your shoes into this place.",
      "You don’t have to wear shoes into this place."
    ],
    "answer": 0,
    "steps": [
      {
        "text": "Dựa vào kiến thức đã học để trả lời.",
        "highlight": null
      }
    ],
    "images": [
      "/images/g7_exams/img_a403bf82.png"
    ]
  },
  "g7-english-67": {
    "id": "g7-english-67",
    "topicId": "g7-english",
    "question": "What does the sign say?",
    "choices": [
      "You shouldn’t speak to anyone in this area.",
      "You don’t have to raise yoyur voice in this area.",
      "You must be quiet in this area.",
      "You mustn’t play in this area."
    ],
    "answer": 0,
    "steps": [
      {
        "text": "Dựa vào kiến thức đã học để trả lời.",
        "highlight": null
      }
    ],
    "images": []
  },
  "g7-english-68": {
    "id": "g7-english-68",
    "topicId": "g7-english",
    "question": "What does the notice say?",
    "choices": [
      "Live music will be played on Saturday nights.",
      "The cafe will have live music on Friday nights starting at"
    ],
    "answer": 0,
    "steps": [
      {
        "text": "Dựa vào kiến thức đã học để trả lời.",
        "highlight": null
      }
    ],
    "images": []
  },
  "g7-english-69": {
    "id": "g7-english-69",
    "topicId": "g7-english",
    "question": "p.m.",
    "choices": [
      "Music will be played only in the morning.",
      "The cafe will not have live music this month."
    ],
    "answer": 0,
    "steps": [
      {
        "text": "Dựa vào kiến thức đã học để trả lời.",
        "highlight": null
      }
    ],
    "images": []
  },
  "g7-english-70": {
    "id": "g7-english-70",
    "topicId": "g7-english",
    "question": "What does the sign say?",
    "choices": [
      "Leave pet waste as it is.",
      "Clean up any waste your pet leaves behind.",
      "Cleaning up pet waste is optional",
      "Only some pet waste needs cleaning"
    ],
    "answer": 0,
    "steps": [
      {
        "text": "Dựa vào kiến thức đã học để trả lời.",
        "highlight": null
      }
    ],
    "images": [
      "/images/g7_exams/img_5a7fc53d.jpeg",
      "/images/g7_exams/img_63ab8914.jpeg"
    ]
  },
  "g7-english-71": {
    "id": "g7-english-71",
    "topicId": "g7-english",
    "question": "What does the sign say?\nI. Read the following announcement and mark the letter A, B, C, or D on your answer sheet to\nindicate the correct option that best fits each of the numbered blanks.\nSOLAR ENERGY WORKSHOP\nThe Green Future Group is happy to announce a free workshop on solar energy this weekend.\nDetails include:\n•\nThe workshop aims to raise (61)  _______ about renewable energy.\n•\nAttendees will learn how (62) ____ and operate solar panels at home.\n•\n(63)____  event will provide informative resources and guides for everyone.\n•\nSeats are limited, so please register (64) ____ advance.",
    "choices": [
      "You can buy burgers and chips today only.",
      "Chips and burgers are free today only.",
      "If you buy a burger today you will get chips for free.",
      "Every burger is served with chips in this restaurant",
      "READING"
    ],
    "answer": 0,
    "steps": [
      {
        "text": "Dựa vào kiến thức đã học để trả lời.",
        "highlight": null
      }
    ],
    "images": []
  },
  "g7-english-72": {
    "id": "g7-english-72",
    "topicId": "g7-english",
    "question": "A. on",
    "choices": [
      "in",
      "at",
      "during"
    ],
    "answer": 0,
    "steps": [
      {
        "text": "Dựa vào kiến thức đã học để trả lời.",
        "highlight": null
      }
    ],
    "images": []
  },
  "g7-english-73": {
    "id": "g7-english-73",
    "topicId": "g7-english",
    "question": "A. an",
    "choices": [
      "a",
      "the",
      "x (no article)"
    ],
    "answer": 0,
    "steps": [
      {
        "text": "Dựa vào kiến thức đã học để trả lời.",
        "highlight": null
      }
    ],
    "images": []
  },
  "g7-english-74": {
    "id": "g7-english-74",
    "topicId": "g7-english",
    "question": "A. activity",
    "choices": [
      "dance",
      "community",
      "statue"
    ],
    "answer": 0,
    "steps": [
      {
        "text": "Dựa vào kiến thức đã học để trả lời.",
        "highlight": null
      }
    ],
    "images": []
  },
  "g7-english-75": {
    "id": "g7-english-75",
    "topicId": "g7-english",
    "question": "A. traditions\nII. Read the following passage and mark the letter A, B, C, or D on your answer sheet to indicate\nthe correct answer to each of the following questions from 31 to 36.",
    "choices": [
      "tradition",
      "traditional",
      "traditionally"
    ],
    "answer": 0,
    "steps": [
      {
        "text": "Dựa vào kiến thức đã học để trả lời.",
        "highlight": null
      }
    ],
    "images": []
  },
  "g7-english-76": {
    "id": "g7-english-76",
    "topicId": "g7-english",
    "question": "What is the main idea of the reading passage?",
    "choices": [
      "What wind is?",
      "Descriptions of wind turbines",
      "How to generate electricity",
      "The role of wind"
    ],
    "answer": 0,
    "steps": [
      {
        "text": "Dựa vào kiến thức đã học để trả lời.",
        "highlight": null
      }
    ],
    "images": []
  },
  "g7-english-77": {
    "id": "g7-english-77",
    "topicId": "g7-english",
    "question": "The word small is OPPOSITE in meaning to _______.",
    "choices": [
      "familiar",
      "tiny",
      "huge",
      "common"
    ],
    "answer": 0,
    "steps": [
      {
        "text": "Dựa vào kiến thức đã học để trả lời.",
        "highlight": null
      }
    ],
    "images": []
  },
  "g7-english-78": {
    "id": "g7-english-78",
    "topicId": "g7-english",
    "question": "What is the reason for the existence of wind?",
    "choices": [
      "atmosphere heated unevenly",
      "wind flow",
      "motion energy",
      "wind turbines"
    ],
    "answer": 0,
    "steps": [
      {
        "text": "Dựa vào kiến thức đã học để trả lời.",
        "highlight": null
      }
    ],
    "images": []
  },
  "g7-english-79": {
    "id": "g7-english-79",
    "topicId": "g7-english",
    "question": "Which of the following is NOT mentioned as a factor affecting the wind direction?",
    "choices": [
      "earth’s terrain",
      "bodies of water",
      "vegetative cover",
      "the Sun"
    ],
    "answer": 0,
    "steps": [
      {
        "text": "Dựa vào kiến thức đã học để trả lời.",
        "highlight": null
      }
    ],
    "images": []
  },
  "g7-english-80": {
    "id": "g7-english-80",
    "topicId": "g7-english",
    "question": "What is the height of the largest wind turbines?",
    "choices": [
      "as tall as a 20-storey building",
      "between 8 and 25 feet",
      "30 feet",
      "50 feet"
    ],
    "answer": 0,
    "steps": [
      {
        "text": "Dựa vào kiến thức đã học để trả lời.",
        "highlight": null
      }
    ],
    "images": []
  },
  "g7-english-81": {
    "id": "g7-english-81",
    "topicId": "g7-english",
    "question": "The word variety is CLOSEST in meaning to _______.",
    "choices": [
      "capacity",
      "popularity",
      "diversity",
      "minority"
    ],
    "answer": 0,
    "steps": [
      {
        "text": "Dựa vào kiến thức đã học để trả lời.",
        "highlight": null
      }
    ],
    "images": []
  },
  "g7-english-82": {
    "id": "g7-english-82",
    "topicId": "g7-english",
    "question": "What is the passage mainly about?",
    "choices": [
      "A famous director with his successful fantasy film.",
      "A young wizard who kills a monster in his magic school.",
      "A film based on the second novel of a fantasy series by J. K. Rowling.",
      "The adventures of a house-elf in a wizarding world."
    ],
    "answer": 0,
    "steps": [
      {
        "text": "Dựa vào kiến thức đã học để trả lời.",
        "highlight": null
      }
    ],
    "images": []
  },
  "g7-english-83": {
    "id": "g7-english-83",
    "topicId": "g7-english",
    "question": "The word “giant” in the text is OPPOSITE  in meaning to ___________.",
    "choices": [
      "huge",
      "tiny",
      "large",
      "awful"
    ],
    "answer": 0,
    "steps": [
      {
        "text": "Dựa vào kiến thức đã học để trả lời.",
        "highlight": null
      }
    ],
    "images": []
  },
  "g7-english-84": {
    "id": "g7-english-84",
    "topicId": "g7-english",
    "question": "The word \"gripping\" in the text is CLOSEST in meaning to ___________.",
    "choices": [
      "moving",
      "frightening",
      "boring",
      "exciting"
    ],
    "answer": 0,
    "steps": [
      {
        "text": "Dựa vào kiến thức đã học để trả lời.",
        "highlight": null
      }
    ],
    "images": []
  },
  "g7-english-85": {
    "id": "g7-english-85",
    "topicId": "g7-english",
    "question": "Which of the following statements about Harry is TRUE?",
    "choices": [
      "He fights against a cruel house-elf of Lord Voldemort.",
      "He kills a giant spider at the end of the film.",
      "He saves Ron’s sister from a basilisk.",
      "He becomes friends with Tom Riddle."
    ],
    "answer": 0,
    "steps": [
      {
        "text": "Dựa vào kiến thức đã học để trả lời.",
        "highlight": null
      }
    ],
    "images": []
  },
  "g7-english-86": {
    "id": "g7-english-86",
    "topicId": "g7-english",
    "question": "What does the word \"It\" in the last sentence refer to?",
    "choices": [
      "The film.",
      "The kind house-elf.",
      "The basilisk.",
      "The  diary."
    ],
    "answer": 0,
    "steps": [
      {
        "text": "Dựa vào kiến thức đã học để trả lời.",
        "highlight": null
      }
    ],
    "images": []
  },
  "g7-english-87": {
    "id": "g7-english-87",
    "topicId": "g7-english",
    "question": "How are the visual effects of the film?\nI. Rewrite the sentence using suggestions in the bracket",
    "choices": [
      "Extremely interesting.",
      "Rather boring.",
      "Very colourful.",
      "Pretty outdated.",
      "WRITING"
    ],
    "answer": 0,
    "steps": [
      {
        "text": "Dựa vào kiến thức đã học để trả lời.",
        "highlight": null
      }
    ],
    "images": []
  },
  "g7-english-88": {
    "id": "g7-english-88",
    "topicId": "g7-english",
    "question": "A. gate",
    "choices": [
      "translation",
      "nation",
      "paint"
    ],
    "answer": 0,
    "steps": [
      {
        "text": "Dựa vào kiến thức đã học để trả lời.",
        "highlight": null
      }
    ],
    "images": []
  },
  "g7-english-89": {
    "id": "g7-english-89",
    "topicId": "g7-english",
    "question": "A. site\nMark the letter A, B, C or D on your answer sheet to indicate the word that differs from the other\nthree in the position of primary stress in each of the following questions.",
    "choices": [
      "twice",
      "side",
      "thin"
    ],
    "answer": 0,
    "steps": [
      {
        "text": "Dựa vào kiến thức đã học để trả lời.",
        "highlight": null
      }
    ],
    "images": []
  },
  "g7-english-90": {
    "id": "g7-english-90",
    "topicId": "g7-english",
    "question": "A. respect",
    "choices": [
      "safety",
      "pavement",
      "traffic"
    ],
    "answer": 0,
    "steps": [
      {
        "text": "Dựa vào kiến thức đã học để trả lời.",
        "highlight": null
      }
    ],
    "images": []
  },
  "g7-english-91": {
    "id": "g7-english-91",
    "topicId": "g7-english",
    "question": "A. illegal\nMark the letter A, B, C or D on your answer sheet to indicate the correct answer to each of the\nfollowing questions.",
    "choices": [
      "prohibitive",
      "noisy",
      "polluted"
    ],
    "answer": 0,
    "steps": [
      {
        "text": "Dựa vào kiến thức đã học để trả lời.",
        "highlight": null
      }
    ],
    "images": []
  },
  "g7-english-92": {
    "id": "g7-english-92",
    "topicId": "g7-english",
    "question": "______he is a CEO and earns a lot of money, he is very mean.",
    "choices": [
      "Because",
      "Although",
      "Despite",
      "Because of"
    ],
    "answer": 0,
    "steps": [
      {
        "text": "Dựa vào kiến thức đã học để trả lời.",
        "highlight": null
      }
    ],
    "images": []
  },
  "g7-english-93": {
    "id": "g7-english-93",
    "topicId": "g7-english",
    "question": "This is a(n) _____ on real life during wars in Vietnam in 1945.",
    "choices": [
      "Horror film",
      "sci-fi",
      "comedy",
      "documentary"
    ],
    "answer": 0,
    "steps": [
      {
        "text": "Dựa vào kiến thức đã học để trả lời.",
        "highlight": null
      }
    ],
    "images": []
  },
  "g7-english-94": {
    "id": "g7-english-94",
    "topicId": "g7-english",
    "question": "The film was so __________. However, my father saw it from beginning to end.",
    "choices": [
      "Interesting",
      "exciting",
      "boring",
      "fascinating"
    ],
    "answer": 0,
    "steps": [
      {
        "text": "Dựa vào kiến thức đã học để trả lời.",
        "highlight": null
      }
    ],
    "images": []
  },
  "g7-english-95": {
    "id": "g7-english-95",
    "topicId": "g7-english",
    "question": "______having a broken leg, she took part in the competition.",
    "choices": [
      "However",
      "Although",
      "In spite of",
      "Because"
    ],
    "answer": 0,
    "steps": [
      {
        "text": "Dựa vào kiến thức đã học để trả lời.",
        "highlight": null
      }
    ],
    "images": []
  },
  "g7-english-96": {
    "id": "g7-english-96",
    "topicId": "g7-english",
    "question": "_______working very hard, he lost his job.",
    "choices": [
      "Despite",
      "However",
      "But",
      "Because"
    ],
    "answer": 0,
    "steps": [
      {
        "text": "Dựa vào kiến thức đã học để trả lời.",
        "highlight": null
      }
    ],
    "images": []
  },
  "g7-english-97": {
    "id": "g7-english-97",
    "topicId": "g7-english",
    "question": "Adam: “How about going to the cinema tonight?” – Linda: “_____”",
    "choices": [
      "That’s a great idea. I’d love to.",
      "That’s an interesting film. I like it",
      "It’s a must-see film. You should watch it",
      "The cinema is quite big."
    ],
    "answer": 0,
    "steps": [
      {
        "text": "Dựa vào kiến thức đã học để trả lời.",
        "highlight": null
      }
    ],
    "images": []
  },
  "g7-english-98": {
    "id": "g7-english-98",
    "topicId": "g7-english",
    "question": "This film made a strong impression _____ me.",
    "choices": [
      "On",
      "in",
      "to",
      "at"
    ],
    "answer": 0,
    "steps": [
      {
        "text": "Dựa vào kiến thức đã học để trả lời.",
        "highlight": null
      }
    ],
    "images": []
  },
  "g7-english-99": {
    "id": "g7-english-99",
    "topicId": "g7-english",
    "question": "Peter wants to _________the BEST ACTOR PRIZE this year.\nRead the following announcement and mark the letter A, B, C or D on your answer sheet to indicate\nthe correct option that best fits each of the numbered blanks from 13 to 16.\nMID-AUTUMN FESTIVAL CELEBRATION\nThe Community Association is (13) ____ to celebrate the annual Mid-Autumn\nFestival this Sunday evening.\nDetails include:\nThe celebration will (14) _____ at the town square.\nVisitors will enjoy traditional lantern displays and (15) ____ mooncakes.\nTickets are free but must be claimed (16) ____ advance.",
    "choices": [
      "Act",
      "direct",
      "perform",
      "win"
    ],
    "answer": 0,
    "steps": [
      {
        "text": "Dựa vào kiến thức đã học để trả lời.",
        "highlight": null
      }
    ],
    "images": []
  },
  "g7-english-100": {
    "id": "g7-english-100",
    "topicId": "g7-english",
    "question": "A. thrilled",
    "choices": [
      "thrilling",
      "thrill",
      "thrilly"
    ],
    "answer": 0,
    "steps": [
      {
        "text": "Dựa vào kiến thức đã học để trả lời.",
        "highlight": null
      }
    ],
    "images": []
  },
  "g7-english-101": {
    "id": "g7-english-101",
    "topicId": "g7-english",
    "question": "A. hold",
    "choices": [
      "take in",
      "take place",
      "bring"
    ],
    "answer": 0,
    "steps": [
      {
        "text": "Dựa vào kiến thức đã học để trả lời.",
        "highlight": null
      }
    ],
    "images": []
  },
  "g7-english-102": {
    "id": "g7-english-102",
    "topicId": "g7-english",
    "question": "A. delicious",
    "choices": [
      "delightful",
      "fine",
      "good"
    ],
    "answer": 0,
    "steps": [
      {
        "text": "Dựa vào kiến thức đã học để trả lời.",
        "highlight": null
      }
    ],
    "images": []
  },
  "g7-english-103": {
    "id": "g7-english-103",
    "topicId": "g7-english",
    "question": "A. in\nMark the letter A, B, C or D on your answer sheet to indicate the correct answer to each of the\nfollowing questions 17.\nMy family joined the spring flower festival last weekend. We were excited to see the beautiful flowers,\nbut __.\na. The festival was more crowded than we expected.\nb. It was difficult to find a parking spot.\nc. We finally got to see the flowers and enjoyed taking pictures.",
    "choices": [
      "on",
      "from",
      "at",
      "b-a-c",
      "a-b-c",
      "c-b-a",
      "b-c-a"
    ],
    "answer": 0,
    "steps": [
      {
        "text": "Dựa vào kiến thức đã học để trả lời.",
        "highlight": null
      }
    ],
    "images": []
  },
  "g7-english-104": {
    "id": "g7-english-104",
    "topicId": "g7-english",
    "question": "Choose the sentence that can end the text in question 17.\nRead the following passage and mark the letter A, B, C or D on your answer sheet to indicate the\ncorrect option that best fits each numbered blank from 19 to 24.\nMost of our energy comes from fossil fuels (19) _____, coal, oil, and natural gas. Although the supplies\nof these energy sources are plentiful, they are limited. The (20) _____ of coal and oil is also having very\nharmful impacts (21) _____ the environment. However, fossil fuels are not the only source of energy\nand burning fuel is not the only way to produce heat and motion. Renewable energy offers us a better\nway.\nSome energy sources are renewable because they are naturally available (22) _____ last forever. Some\nsources have enormous supply so human can never use them up. Moreover, renewable energy sources\nhave much smaller impacts on the environment than fossil and nuclear fuels. (23) _____ include solar\nenergy, which comes from the sun and can be converted into electricity and heat. Wind, geothermal\nenergy from inside the earth, biomass from plants, and hydropower from 1 water are (24) _____\nrenewable sources of energy.",
    "choices": [
      "We had to leave early because it became too crowded.",
      "In the end, we had a wonderful day despite the challenges",
      "The flowers were not as beautiful as we expected",
      "We decided not to go to the festival after all."
    ],
    "answer": 0,
    "steps": [
      {
        "text": "Dựa vào kiến thức đã học để trả lời.",
        "highlight": null
      }
    ],
    "images": []
  },
  "g7-english-105": {
    "id": "g7-english-105",
    "topicId": "g7-english",
    "question": "A. include",
    "choices": [
      "such as",
      "unlike",
      "is"
    ],
    "answer": 0,
    "steps": [
      {
        "text": "Dựa vào kiến thức đã học để trả lời.",
        "highlight": null
      }
    ],
    "images": [
      "/images/g7_exams/img_a2014ebb.png"
    ]
  },
  "g7-english-106": {
    "id": "g7-english-106",
    "topicId": "g7-english",
    "question": "A. burn",
    "choices": [
      "to burn",
      "burns",
      "burning"
    ],
    "answer": 0,
    "steps": [
      {
        "text": "Dựa vào kiến thức đã học để trả lời.",
        "highlight": null
      }
    ],
    "images": []
  },
  "g7-english-107": {
    "id": "g7-english-107",
    "topicId": "g7-english",
    "question": "A. at",
    "choices": [
      "of",
      "on",
      "in"
    ],
    "answer": 0,
    "steps": [
      {
        "text": "Dựa vào kiến thức đã học để trả lời.",
        "highlight": null
      }
    ],
    "images": []
  },
  "g7-english-108": {
    "id": "g7-english-108",
    "topicId": "g7-english",
    "question": "A. so",
    "choices": [
      "but",
      "for",
      "and"
    ],
    "answer": 0,
    "steps": [
      {
        "text": "Dựa vào kiến thức đã học để trả lời.",
        "highlight": null
      }
    ],
    "images": []
  },
  "g7-english-109": {
    "id": "g7-english-109",
    "topicId": "g7-english",
    "question": "A. It",
    "choices": [
      "There",
      "That",
      "They"
    ],
    "answer": 0,
    "steps": [
      {
        "text": "Dựa vào kiến thức đã học để trả lời.",
        "highlight": null
      }
    ],
    "images": []
  },
  "g7-english-110": {
    "id": "g7-english-110",
    "topicId": "g7-english",
    "question": "A. also\nMark the letter A, B, C or D on your answer sheet to indicate the sentence that is closest in meaning\nto the\nRead the following sign or notice and mark the letter A, B, C or D on your answer sheet to indicate\nthe correct answer to each of the following questions.",
    "choices": [
      "only",
      "last",
      "then"
    ],
    "answer": 0,
    "steps": [
      {
        "text": "Dựa vào kiến thức đã học để trả lời.",
        "highlight": null
      }
    ],
    "images": [
      "/images/g7_exams/img_5b8604ad.jpeg"
    ]
  },
  "g7-english-111": {
    "id": "g7-english-111",
    "topicId": "g7-english",
    "question": "What does the notice say?",
    "choices": [
      "You can only use the bridge until June.",
      "Repairs to the bridge will start at the end of June.",
      "From July on, you can drive across the bridge.",
      "You are allowed to use the bridge during June."
    ],
    "answer": 0,
    "steps": [
      {
        "text": "Dựa vào kiến thức đã học để trả lời.",
        "highlight": null
      }
    ],
    "images": []
  },
  "g7-english-112": {
    "id": "g7-english-112",
    "topicId": "g7-english",
    "question": "What does the sign say?\nRead the following passage and mark the letter A, B, C or D on your answer sheet to indicate the\ncorrect answer to each of the following questions.\nTwenty years ago, you needed to bring along air tickets, vouchers, travel cheques, and a heavy\ncarry-on bag with Walkman, CDs, travel journal and etc. The load is so much lighter now since most\nstuff can be stored in our tablets or smartphones. Technology is amazing isn't it?\nAirport security was a brief back then. They used metal cutleries and gave all passengers bags of\ntoiletries to keep them comfortable during the flight. Now, there are many limitations on things that we\ncan and cannot bring on board. Thanks to \"Everyone can fly\" tagline, airlines had to reduce their\nservices to stay afloat. So more people can fly and travel now.\nTwo decades ago, if you wish to call home, you can only do it at an International\nTelecommunications Exchange and dial you home number with no guarantee that it will get through.\nThese days, all we need to stop by upon arrival is a local SIM card available as you walk out of the\ndeparture hall. The Internet makes it easy for you to Skype, Facetime your family just to inform them\nthat you have arrived safely.",
    "choices": [
      "No pedestrian traffic.",
      "No playing in the street.",
      "No passing allowed.",
      "No parking allowed."
    ],
    "answer": 0,
    "steps": [
      {
        "text": "Dựa vào kiến thức đã học để trả lời.",
        "highlight": null
      }
    ],
    "images": []
  },
  "g7-english-113": {
    "id": "g7-english-113",
    "topicId": "g7-english",
    "question": "What is the main idea of the passage?",
    "choices": [
      "Travelling in the past",
      "Travelling now",
      "Travelling in the past and now",
      "Travelling tomorrow."
    ],
    "answer": 0,
    "steps": [
      {
        "text": "Dựa vào kiến thức đã học để trả lời.",
        "highlight": null
      }
    ],
    "images": []
  },
  "g7-english-114": {
    "id": "g7-english-114",
    "topicId": "g7-english",
    "question": "What is one important thing to bring along in your trip now?",
    "choices": [
      "Travel cheques",
      "your smartphone",
      "Travel journal",
      "Travel car"
    ],
    "answer": 0,
    "steps": [
      {
        "text": "Dựa vào kiến thức đã học để trả lời.",
        "highlight": null
      }
    ],
    "images": []
  },
  "g7-english-115": {
    "id": "g7-english-115",
    "topicId": "g7-english",
    "question": "The number of travelers is ______.",
    "choices": [
      "the same as in the past",
      "lower now than in the past",
      "higher now than in the past",
      "high now than in the past"
    ],
    "answer": 0,
    "steps": [
      {
        "text": "Dựa vào kiến thức đã học để trả lời.",
        "highlight": null
      }
    ],
    "images": []
  },
  "g7-english-116": {
    "id": "g7-english-116",
    "topicId": "g7-english",
    "question": "Which of the following statement is NOT TRUE according to the passage?",
    "choices": [
      "The load that needs bringing is now lighter than in the past.",
      "Metal cutleries are used to keep comfortable.",
      "In these days, you still only make a call to home at International Telecommunications Exchange.",
      "Skype and Facetime are useful for keeping contact with your family."
    ],
    "answer": 0,
    "steps": [
      {
        "text": "Dựa vào kiến thức đã học để trả lời.",
        "highlight": null
      }
    ],
    "images": []
  },
  "g7-english-117": {
    "id": "g7-english-117",
    "topicId": "g7-english",
    "question": "The word “stuff” is CLOSEST in meaning to ________.",
    "choices": [
      "Object",
      "airlines",
      "service",
      "store"
    ],
    "answer": 0,
    "steps": [
      {
        "text": "Dựa vào kiến thức đã học để trả lời.",
        "highlight": null
      }
    ],
    "images": []
  },
  "g7-english-118": {
    "id": "g7-english-118",
    "topicId": "g7-english",
    "question": "The word “available” is OPPOSITE in meaning to _________.\nWrite the correst tense or form of the word in the brackets.",
    "choices": [
      "Rare",
      "abundant",
      "existing",
      "easy"
    ],
    "answer": 0,
    "steps": [
      {
        "text": "Dựa vào kiến thức đã học để trả lời.",
        "highlight": null
      }
    ],
    "images": []
  },
  "g7-english-119": {
    "id": "g7-english-119",
    "topicId": "g7-english",
    "question": "Using non-renewable energy sources like coal, oil ___________ a lot of carbon dioxide\n(produce).",
    "choices": [],
    "answer": 0,
    "steps": [
      {
        "text": "Dựa vào kiến thức đã học để trả lời.",
        "highlight": null
      }
    ],
    "images": [],
    "type": "essay"
  },
  "g7-english-120": {
    "id": "g7-english-120",
    "topicId": "g7-english",
    "question": "Renewable sources _____________from the sun, wind or water. (come)",
    "choices": [],
    "answer": 0,
    "steps": [
      {
        "text": "Dựa vào kiến thức đã học để trả lời.",
        "highlight": null
      }
    ],
    "images": [],
    "type": "essay"
  },
  "g7-english-121": {
    "id": "g7-english-121",
    "topicId": "g7-english",
    "question": "In the future we  _______ more on renewable energy sources. (rely)\nRewrite the following sentences using the words in brackets giving the same meaning.",
    "choices": [],
    "answer": 0,
    "steps": [
      {
        "text": "Dựa vào kiến thức đã học để trả lời.",
        "highlight": null
      }
    ],
    "images": [],
    "type": "essay"
  },
  "g7-english-122": {
    "id": "g7-english-122",
    "topicId": "g7-english",
    "question": "Tom enjoys playing the guitar in his free time.\nTom is_______________________________________________________",
    "choices": [],
    "answer": 0,
    "steps": [
      {
        "text": "Dựa vào kiến thức đã học để trả lời.",
        "highlight": null
      }
    ],
    "images": [],
    "type": "essay"
  },
  "g7-english-123": {
    "id": "g7-english-123",
    "topicId": "g7-english",
    "question": "In England, driving on the right side of the road is against the laws.\nYou mustn’t________________________________________________________",
    "choices": [],
    "answer": 0,
    "steps": [
      {
        "text": "Dựa vào kiến thức đã học để trả lời.",
        "highlight": null
      }
    ],
    "images": [],
    "type": "essay"
  },
  "g7-english-124": {
    "id": "g7-english-124",
    "topicId": "g7-english",
    "question": "She spends thirty minutes doing this test.\nIt takes________________________________________________________\nUse the given words/ phrases to make the sentences.",
    "choices": [],
    "answer": 0,
    "steps": [
      {
        "text": "Dựa vào kiến thức đã học để trả lời.",
        "highlight": null
      }
    ],
    "images": [],
    "type": "essay"
  },
  "g7-english-125": {
    "id": "g7-english-125",
    "topicId": "g7-english",
    "question": "Robot/ help/ people/ do/ household chores.\n________________________________________________________",
    "choices": [],
    "answer": 0,
    "steps": [
      {
        "text": "Dựa vào kiến thức đã học để trả lời.",
        "highlight": null
      }
    ],
    "images": [],
    "type": "essay"
  },
  "g7-english-126": {
    "id": "g7-english-126",
    "topicId": "g7-english",
    "question": "Almost all our energy/ come/ oil/ gas/ natural gas.\n______________________________________________________\n-The end-",
    "choices": [],
    "answer": 0,
    "steps": [
      {
        "text": "Dựa vào kiến thức đã học để trả lời.",
        "highlight": null
      }
    ],
    "images": [],
    "type": "essay"
  },
  "g7-math-1": {
    "id": "g7-math-1",
    "topicId": "g7-math",
    "question": "Tổng sản lượng cà phê xuất khẩu của Việt Nam trong giai đoạn 2015 – 2018 là bao nhiêu nghìn\ntấn?",
    "choices": [
      "4 563 nghìn tấn;",
      "6 445 nghìn tấn;",
      "3 222 nghìn tấn;",
      "5 104 nghìn tấn."
    ],
    "answer": 0,
    "steps": [
      {
        "text": "Dựa vào kiến thức đã học để trả lời.",
        "highlight": null
      }
    ],
    "images": [
      "/images/g7_exams/img_9c7fbe03.jpeg"
    ]
  },
  "g7-math-2": {
    "id": "g7-math-2",
    "topicId": "g7-math",
    "question": "Nếu quy ước rằng, sản lượng xuất khẩu cà phê trên 1 700 nghìn tấn là xuất siêu thì những năm\nnào Việt Nam đạt sản lượng xuất khẩu xuất siêu?",
    "choices": [
      "2012;",
      "2016;",
      "2018;",
      "Cả A, B, C đều đúng."
    ],
    "answer": 0,
    "steps": [
      {
        "text": "Dựa vào kiến thức đã học để trả lời.",
        "highlight": null
      }
    ],
    "images": []
  },
  "g7-math-3": {
    "id": "g7-math-3",
    "topicId": "g7-math",
    "question": "Sản lượng cà phê xuất khẩu của Việt Nam năm 2017 giảm so với năm 2016 (làm tròn kết quả\nđến hàng đơn vị là)\nSử dụng biểu đồ biểu diễn kết quả học tập Học kì I (tính theo tỉ số phần\ntrăm) của học sinh lớp 7A ở hình bên để trả lời Câu 4, 5, 6",
    "choices": [
      "81%",
      "20%",
      "19%",
      "18%"
    ],
    "answer": 0,
    "steps": [
      {
        "text": "Dựa vào kiến thức đã học để trả lời.",
        "highlight": null
      }
    ],
    "images": []
  },
  "g7-math-4": {
    "id": "g7-math-4",
    "topicId": "g7-math",
    "question": "Học sinh lớp 7A có kết quả học tập Học kì I được đánh giá ở mức\nTốt chiếm số phần trăm so với cả lớp là",
    "choices": [
      "3%.",
      "5%.",
      "25%.",
      "57%."
    ],
    "answer": 0,
    "steps": [
      {
        "text": "Dựa vào kiến thức đã học để trả lời.",
        "highlight": null
      }
    ],
    "images": []
  },
  "g7-math-5": {
    "id": "g7-math-5",
    "topicId": "g7-math",
    "question": "Tổng số học sinh lớp 7A là 40 học sinh. Số học sinh xếp loại đạt của\nlớp 7A là:",
    "choices": [
      "12",
      "13",
      "14"
    ],
    "answer": 0,
    "steps": [
      {
        "text": "Dựa vào kiến thức đã học để trả lời.",
        "highlight": null
      }
    ],
    "images": []
  },
  "g7-math-6": {
    "id": "g7-math-6",
    "topicId": "g7-math",
    "question": "Tổng số học sinh có kết quả học tập Học kì I được đánh giá ở mức Đạt và Chưa đạt bằng bao\nnhiêu phần trăm tổng số học sinh có kết quả học tập được đánh giá ở mức Tốt và Khá (làm tròn kết quả\nđến hàng phần mười)?",
    "choices": [
      "61,3%",
      "62%",
      "25%"
    ],
    "answer": 0,
    "steps": [
      {
        "text": "Dựa vào kiến thức đã học để trả lời.",
        "highlight": null
      }
    ],
    "images": []
  },
  "g7-math-7": {
    "id": "g7-math-7",
    "topicId": "g7-math",
    "question": "Gieo ngẫu nhiên xúc xắc một lần. Xác suất của biến cố “Mặt xuất hiện của xúc xắc có số chấm\nlà số chia hết cho 3” là",
    "choices": [
      "1"
    ],
    "answer": 0,
    "steps": [
      {
        "text": "Dựa vào kiến thức đã học để trả lời.",
        "highlight": null
      }
    ],
    "images": []
  },
  "g7-math-8": {
    "id": "g7-math-8",
    "topicId": "g7-math",
    "question": "Một hộp có 100 chiếc thẻ cùng loại, mỗi thẻ được ghi một trong các số 100; 101;….. ;199; hai\nthẻ khác nhau thì ghi hai số khác nhau. Rút ngẫu nhiên một thẻ trong hộp. Xác suất của biến cố “Số\nxuất hiện trên thẻ được rút ra là số có tổng ba chữ số bằng 12” là",
    "choices": [
      "2"
    ],
    "answer": 0,
    "steps": [
      {
        "text": "Dựa vào kiến thức đã học để trả lời.",
        "highlight": null
      }
    ],
    "images": []
  },
  "g7-math-9": {
    "id": "g7-math-9",
    "topicId": "g7-math",
    "question": "Sắp xếp đa thức\n\n3\n4\n2\n3\n5\n4\n7\n2\nQ x\nx\nx\nx\nx\n\n\n\n\n theo lũy thừa tăng dần của biến x\nA.\n\n4\n3\n2\n3\n5\n4\n7\n2\nQ x\nx\nx\nx\nx\n\n\n\n\n\nB.\n\n3\n2\n4\n3\n7\n4\n5\n2\nQ x\nx\nx\nx\nx\n\n\n\n\n\nC.\n\n2\n3\n4\n3\n7\n4\n5\n2\nQ x\nx\nx\nx\nx\n\n\n\n\n\nD.\n\n2\n3\n4\n3\n7\n4\n5\n2\nQ x\nx\nx\nx\nx\n\n\n\n\n",
    "choices": [],
    "answer": 0,
    "steps": [
      {
        "text": "Dựa vào kiến thức đã học để trả lời.",
        "highlight": null
      }
    ],
    "images": [],
    "type": "essay"
  },
  "g7-math-10": {
    "id": "g7-math-10",
    "topicId": "g7-math",
    "question": "Bậc của đa thức\n\n3\n4\n126\n512\n20\n1\nH x\nx\nx\nx\n\n\n\n là:",
    "choices": [
      "4",
      "3",
      "1",
      "0"
    ],
    "answer": 0,
    "steps": [
      {
        "text": "Dựa vào kiến thức đã học để trả lời.",
        "highlight": null
      }
    ],
    "images": []
  },
  "g7-math-11": {
    "id": "g7-math-11",
    "topicId": "g7-math",
    "question": "Hệ số cao nhất và hệ số tự do của đa thức\n5\n4\n2\n( )\n8\n2\n3\n7\n2\nP x\nx\nx\nx\nx\n\n\n\n\n là:\n",
    "choices": [
      "8và  2",
      "3 và 7",
      "2",
      "2  và  2"
    ],
    "answer": 0,
    "steps": [
      {
        "text": "Dựa vào kiến thức đã học để trả lời.",
        "highlight": null
      }
    ],
    "images": []
  },
  "g7-math-12": {
    "id": "g7-math-12",
    "topicId": "g7-math",
    "question": "Trong các số 2\n;\n1\n2\n\n; 1; 2  thì số nào không là nghiệm của đa thức\n3\n2\n4\n4\n( )\nP x\nx\nx\nx\n\n\n\n\n?\n                        B.\n1\n2\n",
    "choices": [
      "2",
      "1",
      "2"
    ],
    "answer": 0,
    "steps": [
      {
        "text": "Dựa vào kiến thức đã học để trả lời.",
        "highlight": null
      }
    ],
    "images": []
  },
  "g7-math-13": {
    "id": "g7-math-13",
    "topicId": "g7-math",
    "question": "Biểu thức đại số biểu thị cho tổng các bình phương của x  và y  là:\nA.\n2\n2\nx\ny\n\nB.\n2\nx\ny\n\nC.\n2x\ny\n\n\n2\nx\ny\n",
    "choices": [
      ""
    ],
    "answer": 0,
    "steps": [
      {
        "text": "Dựa vào kiến thức đã học để trả lời.",
        "highlight": null
      }
    ],
    "images": []
  },
  "g7-math-14": {
    "id": "g7-math-14",
    "topicId": "g7-math",
    "question": "Bậc của đa thức:\n\n4\n3\n4\n2\n4\n5\n4\n2\n7\n3\nM x\nx\nx\nx\nx\nx\nx\n\n\n\n\n\n\n là:",
    "choices": [
      "7",
      "4",
      "3",
      "5"
    ],
    "answer": 0,
    "steps": [
      {
        "text": "Dựa vào kiến thức đã học để trả lời.",
        "highlight": null
      }
    ],
    "images": [
      "/images/g7_exams/img_4d96d139.jpeg"
    ]
  },
  "g7-math-15": {
    "id": "g7-math-15",
    "topicId": "g7-math",
    "question": "Giá trị của biểu thức\n3x\nxy\n\ntại\n2\nx \n;\n3\n2\ny\n\n\nlà:",
    "choices": [
      "3",
      "5",
      "9",
      "11"
    ],
    "answer": 0,
    "steps": [
      {
        "text": "Dựa vào kiến thức đã học để trả lời.",
        "highlight": null
      }
    ],
    "images": []
  },
  "g7-math-16": {
    "id": "g7-math-16",
    "topicId": "g7-math",
    "question": "Đa thức\n2\n( )\n6\nA x\nx\nax\n\n\n có nghiệm\n3\nx  thì a  bằng:",
    "choices": [
      "1",
      "1",
      "2",
      "5"
    ],
    "answer": 0,
    "steps": [
      {
        "text": "Dựa vào kiến thức đã học để trả lời.",
        "highlight": null
      }
    ],
    "images": []
  },
  "g7-math-17": {
    "id": "g7-math-17",
    "topicId": "g7-math",
    "question": "Hình hộp chữ nhật có mấy mặt?",
    "choices": [
      "6",
      "5",
      "4",
      "7"
    ],
    "answer": 0,
    "steps": [
      {
        "text": "Dựa vào kiến thức đã học để trả lời.",
        "highlight": null
      }
    ],
    "images": []
  },
  "g7-math-18": {
    "id": "g7-math-18",
    "topicId": "g7-math",
    "question": "Cho hình hộp chữ nhật\n.\nABCD A B C D\n. Mặt phẳng nào sau\nđây không là mặt của hình hộp chữ nhật?\n\n\n",
    "choices": [
      "mặt phẳng ABCD",
      "mặt phẳng CC DD",
      "mặt phẳng ABB A",
      "mặt phẳng ABC D"
    ],
    "answer": 0,
    "steps": [
      {
        "text": "Dựa vào kiến thức đã học để trả lời.",
        "highlight": null
      }
    ],
    "images": []
  },
  "g7-math-19": {
    "id": "g7-math-19",
    "topicId": "g7-math",
    "question": "Khẳng định nào sau đây đúng?",
    "choices": [
      "Các mặt bên của hình lăng trụ đứng tứ giác là các hình chữ nhật.",
      "Các mặt bên của hình lăng trụ đứng tam giác là các hình tam giác.",
      "Hình lăng trụ đứng tam giác có năm mặt bên.",
      "Hình lăng trụ đứng tam giác có bốn mặt bên."
    ],
    "answer": 0,
    "steps": [
      {
        "text": "Dựa vào kiến thức đã học để trả lời.",
        "highlight": null
      }
    ],
    "images": []
  },
  "g7-math-20": {
    "id": "g7-math-20",
    "topicId": "g7-math",
    "question": "Một cục tẩy có dạng hình hộp chữ nhật với các kích thước của cạnh đáy là 5cm, 3 cm và chiều\ncao là 1,5 cm. Tính diện tích xung quanh của cục tẩy đó?\n3",
    "choices": [
      "24 cm2;",
      "18 cm2;",
      "5 cm2;",
      "6 cm2."
    ],
    "answer": 0,
    "steps": [
      {
        "text": "Dựa vào kiến thức đã học để trả lời.",
        "highlight": null
      }
    ],
    "images": []
  },
  "g7-math-21": {
    "id": "g7-math-21",
    "topicId": "g7-math",
    "question": "Diện tích xung quanh của hình lập phương có cạnh 2,5 m  là:\nA.\n2",
    "choices": [],
    "answer": 0,
    "steps": [
      {
        "text": "Dựa vào kiến thức đã học để trả lời.",
        "highlight": null
      }
    ],
    "images": [
      "/images/g7_exams/img_e4cbdf07.jpeg",
      "/images/g7_exams/img_4c34e3be.jpeg"
    ],
    "type": "essay"
  },
  "g7-math-22": {
    "id": "g7-math-22",
    "topicId": "g7-math",
    "question": "Cho hình lăng trụ đứng có đáy là hình tam giác (như hình vẽ). Diện\ntích xung quanh của hình lăng trụ trên là:\nA.\n2",
    "choices": [],
    "answer": 0,
    "steps": [
      {
        "text": "Dựa vào kiến thức đã học để trả lời.",
        "highlight": null
      }
    ],
    "images": [],
    "type": "essay"
  },
  "g7-math-23": {
    "id": "g7-math-23",
    "topicId": "g7-math",
    "question": "Một bể nước có dạng hình hộp chữ nhậtcó các kích thước của đáy\nlà 5 m, 12 m và chiều cao là 9m. Thể tích của bể nước đó bằng:",
    "choices": [
      "306 m3;",
      "336 m3;",
      "540 m3;",
      "153 m3."
    ],
    "answer": 0,
    "steps": [
      {
        "text": "Dựa vào kiến thức đã học để trả lời.",
        "highlight": null
      }
    ],
    "images": []
  },
  "g7-math-24": {
    "id": "g7-math-24",
    "topicId": "g7-math",
    "question": "Cho túp lều có các kích thước như hình vẽ. Tính số vải cần để dựng\nđược túp lều (tính cả số vải để trải nền đất). Biết cửa của túp lều có hai cạnh\nbên bằng nhau.",
    "choices": [
      "5 m2;",
      "5 m;",
      "10 m2;",
      "10,6 m2."
    ],
    "answer": 0,
    "steps": [
      {
        "text": "Dựa vào kiến thức đã học để trả lời.",
        "highlight": null
      }
    ],
    "images": []
  },
  "g7-math-25": {
    "id": "g7-math-25",
    "topicId": "g7-math",
    "question": "Gọi I là giao điểm của ba đường phân giác của tam giác.\nKết luận nào sau đây là đúng?",
    "choices": [
      "I cách đều 3 cạnh của tam giác.",
      "I cách dều ba đỉnh của tam giác.",
      "I là trọng tâm của tam giác.",
      "1 là trực tâm cùa tam giác."
    ],
    "answer": 0,
    "steps": [
      {
        "text": "Dựa vào kiến thức đã học để trả lời.",
        "highlight": null
      }
    ],
    "images": []
  },
  "g7-math-26": {
    "id": "g7-math-26",
    "topicId": "g7-math",
    "question": "Một tam giác có độ dài ba cạnh đều là số nguyên. Cạnh lớn nhất bằng 7cm, cạnh nhỏ nhất\nbằng 2cm. Khi đó cạnh còn lại của tam giác bằng:",
    "choices": [
      "3 cm",
      "4 cm",
      "5 cm",
      "6 cm"
    ],
    "answer": 0,
    "steps": [
      {
        "text": "Dựa vào kiến thức đã học để trả lời.",
        "highlight": null
      }
    ],
    "images": []
  },
  "g7-math-27": {
    "id": "g7-math-27",
    "topicId": "g7-math",
    "question": "Tam  giác cân có góc ở đỉnh là 1000 thì góc ở đáy là:",
    "choices": [
      "650",
      "1000",
      "800"
    ],
    "answer": 0,
    "steps": [
      {
        "text": "Dựa vào kiến thức đã học để trả lời.",
        "highlight": null
      }
    ],
    "images": []
  },
  "g7-math-28": {
    "id": "g7-math-28",
    "topicId": "g7-math",
    "question": "Cho ∆ABC biết \n0\nA\n50\n\n; \n0\nB\n120\n\n. Khi đó ta có:",
    "choices": [
      "AC > BC > AB",
      "AB > BC > AC",
      "BC > AC > AB",
      "AC > AB > BC"
    ],
    "answer": 0,
    "steps": [
      {
        "text": "Dựa vào kiến thức đã học để trả lời.",
        "highlight": null
      }
    ],
    "images": [
      "/images/g7_exams/img_5df3bfea.jpeg"
    ]
  },
  "g7-math-29": {
    "id": "g7-math-29",
    "topicId": "g7-math",
    "question": "Cho ∆ABC có đường trung tuyến AD, G là trọng tâm. Trong các khẳng định sau, khẳng định\nnào đúng?\n1\nGA\n3\n\n2\nDG \n1\nDA\n3\n\n2\nGA ",
    "choices": [
      "GD",
      "AD",
      "DG",
      "AD"
    ],
    "answer": 0,
    "steps": [
      {
        "text": "Dựa vào kiến thức đã học để trả lời.",
        "highlight": null
      }
    ],
    "images": []
  },
  "g7-math-30": {
    "id": "g7-math-30",
    "topicId": "g7-math",
    "question": "Giao điểm của hai đường cao trong một tam giác gọi là :",
    "choices": [
      "Trọng tâm của tam giác",
      "Trực tâm của tam giác.",
      "Tâm đường tròn ngoại tiếp tam giác",
      "Tâm đường tròn ngoại tiếp tam giác."
    ],
    "answer": 0,
    "steps": [
      {
        "text": "Dựa vào kiến thức đã học để trả lời.",
        "highlight": null
      }
    ],
    "images": []
  },
  "g7-math-31": {
    "id": "g7-math-31",
    "topicId": "g7-math",
    "question": "Quan sát hình vẽ sau. Khẳng định nào là đúng\ndưới đây?",
    "choices": [
      "Đường vuông góc kẻ từ A xuống d  là BC .",
      "Chân đường vuông góc kẻ từ P  xuống d  là H .",
      "Chỉ có 1 đường xiên kẻ từ A xuống đường thẳng d",
      "Điểm B  là hình chiếu của A xuống đường thẳng d"
    ],
    "answer": 0,
    "steps": [
      {
        "text": "Dựa vào kiến thức đã học để trả lời.",
        "highlight": null
      }
    ],
    "images": []
  },
  "g7-math-32": {
    "id": "g7-math-32",
    "topicId": "g7-math",
    "question": "Cho ABC\n\ncó M là trung điểm của BC; G là trọng tâm và AM = 12cm. Độ dài đoạn thẳng\nAG bằng?\n4",
    "choices": [
      "8cm",
      "6cm",
      "4cm",
      "3cm."
    ],
    "answer": 0,
    "steps": [
      {
        "text": "Dựa vào kiến thức đã học để trả lời.",
        "highlight": null
      }
    ],
    "images": []
  },
  "g7-math-33": {
    "id": "g7-math-33",
    "topicId": "g7-math",
    "question": "Cho tam giác ABC  có\n,\nAM BN  là hai đường trung tuyến, G  là trọng tâm, khi đó ta có\nA.\n2\nAG\nGM\n\n.\nB.\n2\nGM\nAM\n\n.\nC.\n1\n2\nAG\nAB\n\n.\nD.\n6\nAG\nGM\n\n.",
    "choices": [],
    "answer": 0,
    "steps": [
      {
        "text": "Dựa vào kiến thức đã học để trả lời.",
        "highlight": null
      }
    ],
    "images": [],
    "type": "essay"
  },
  "g7-math-34": {
    "id": "g7-math-34",
    "topicId": "g7-math",
    "question": "Cho tam giác ABC  có\n5cm,\n10cm,\n8cm\n\n\n\nAB\nAC\nBC\nthì:\n\n\n\n\nB\nC\nA.\n\n\n\n\nC\nA\n\n\n\n\nC\nB\nA.\n\n\n\n\nB\nA\nC .",
    "choices": [
      "",
      "",
      "",
      "",
      ""
    ],
    "answer": 0,
    "steps": [
      {
        "text": "Dựa vào kiến thức đã học để trả lời.",
        "highlight": null
      }
    ],
    "images": []
  },
  "g7-math-35": {
    "id": "g7-math-35",
    "topicId": "g7-math",
    "question": "Tam  giác vuông cân có góc ở đáy bằng:\nII. BÀI TẬP TỰ LUẬN",
    "choices": [
      "300",
      "450",
      "600",
      "900",
      "ĐẠI SỐ"
    ],
    "answer": 0,
    "steps": [
      {
        "text": "Dựa vào kiến thức đã học để trả lời.",
        "highlight": null
      }
    ],
    "images": []
  },
  "g7-math-36": {
    "id": "g7-math-36",
    "topicId": "g7-math",
    "question": "Dùng biểu thức toán học để biểu thị các tình huống sau:\na) Một cuốn vở viết giá 5000 đồng. Hỏi mua x  cuốn vở viết như thế hết bao nhiêu tiền?\nb) Năm nay thầy giáo 40 tuổi. Hỏi x  năm nữa thầy giáo bao nhiêu tuổi?\nc) Một người chạy thể dục buổi sáng với vận tốc trung bình x \n\n/\nkm h , mỗi sáng người đó chạy nửa\ngiờ. Hỏi trung bình mỗi sáng người đó chạy thể dục được bao nhiêu km?\nd) Một mảnh đất hình chữ nhật có chiều dài là x  mét, chiều rộng kém chiều dài 20 mét. Tính chu vi\nmảnh đất.\ne) Một hình thang có độ dài đáy lớn là x  mét, đáy bé có độ dài nhỏ hơn đáy lớn 5 mét, chiều cao gấp",
    "choices": [],
    "answer": 0,
    "steps": [
      {
        "text": "Dựa vào kiến thức đã học để trả lời.",
        "highlight": null
      }
    ],
    "images": [],
    "type": "essay"
  },
  "g7-math-37": {
    "id": "g7-math-37",
    "topicId": "g7-math",
    "question": "Cho biểu thức\n3\n4\n1\nA\nx y\n2xy\n3\n4\n\n\n\n. Tính giá trị của A biết x = -1 và y = 2.",
    "choices": [],
    "answer": 0,
    "steps": [
      {
        "text": "Dựa vào kiến thức đã học để trả lời.",
        "highlight": null
      }
    ],
    "images": [],
    "type": "essay"
  },
  "g7-math-38": {
    "id": "g7-math-38",
    "topicId": "g7-math",
    "question": "Cho biểu thức\n3\n4\n4\n3\n3\nB\n3x y\n3x y\n2x\n2y\n4\n\n\n\n\n\n. Tính giá trị của B biết x – y = 0.",
    "choices": [],
    "answer": 0,
    "steps": [
      {
        "text": "Dựa vào kiến thức đã học để trả lời.",
        "highlight": null
      }
    ],
    "images": [],
    "type": "essay"
  },
  "g7-math-39": {
    "id": "g7-math-39",
    "topicId": "g7-math",
    "question": "Tìm nghiệm của các đa thức sau:\n2\n2\n2\n( )\n2\n1;\n(x)\n5",
    "choices": [],
    "answer": 0,
    "steps": [
      {
        "text": "Dựa vào kiến thức đã học để trả lời.",
        "highlight": null
      }
    ],
    "images": [],
    "type": "essay"
  },
  "g7-math-40": {
    "id": "g7-math-40",
    "topicId": "g7-math",
    "question": "Chứng tỏ các đa thức sau không có nghiệm:\na)\n2\n5;\nx \nb)\n2\n3\n7;\nx \nc)\n2\n5\n16.\nx\n\n\nd)\n4\n3\n10.\nx\n\n",
    "choices": [],
    "answer": 0,
    "steps": [
      {
        "text": "Dựa vào kiến thức đã học để trả lời.",
        "highlight": null
      }
    ],
    "images": [],
    "type": "essay"
  },
  "g7-math-41": {
    "id": "g7-math-41",
    "topicId": "g7-math",
    "question": "Cho hai đa thức\n\n4\n3\n2\n5\n8\nF x\nx\nx\nx\n\n\n và\n\n4\n2\n3\n9\nG x\nx\nx\nx\n\n\n\n.\na) Tìm đa thức\n\nH x  sao cho\n\n\n\nH x\nG x\nF x\n\n\nb) Tìm đa thức\n\nR x  sao cho\n\n\n\nF x\nR x\nG x\n\n",
    "choices": [],
    "answer": 0,
    "steps": [
      {
        "text": "Dựa vào kiến thức đã học để trả lời.",
        "highlight": null
      }
    ],
    "images": [],
    "type": "essay"
  },
  "g7-math-42": {
    "id": "g7-math-42",
    "topicId": "g7-math",
    "question": "Cho hai đa thức\n\n3\n2\n2\n3\n4\n7\n3\n9\nM x\nx\nx\nx\nx\nx\n\n\n\n\n\n\n\n3\n2\n2\n3\n6\n5\n6\n3\n2\n2\nN x\nx\nx\nx\nx\nx\n\n\n\n\n\n\na) Thu gọn và sắp xếp hai đa thức theo lũy thừa giảm của biến\nb) Tính \n\n\nP x\nM x\nN x\n\n\nvà\n\n\n\nQ x\nM x\nN x\n\n\nc) Tính các giá trị \n0\nP\n; \n1\nP \n; \n2\nP",
    "choices": [],
    "answer": 0,
    "steps": [
      {
        "text": "Dựa vào kiến thức đã học để trả lời.",
        "highlight": null
      }
    ],
    "images": [],
    "type": "essay"
  },
  "g7-math-43": {
    "id": "g7-math-43",
    "topicId": "g7-math",
    "question": "Cho các đa thức: A(x) = x3 – 2x2 + 3x +1; B(x) =  x3 + x – 1; C(x) = 2x2 – 1.\na) Tính A(x) – B(x) + C(x)\nb) Tìm x sao cho A(x) – B(x) + C(x) = 0",
    "choices": [],
    "answer": 0,
    "steps": [
      {
        "text": "Dựa vào kiến thức đã học để trả lời.",
        "highlight": null
      }
    ],
    "images": [],
    "type": "essay"
  },
  "g7-math-44": {
    "id": "g7-math-44",
    "topicId": "g7-math",
    "question": "Cho hai đa thức:\nA(x) = x2 + 4x - x5 - 7x4 – 2x3  + 9  và   B(x) = 2x3 + 2x2 + x5 + 7x4 – 3x – 9\na) Sắp xếp các đa thức theo luỹ thừa giảm dần của biến:\n5\nb) Tính tổng H(x) = A(x) + B(x)\nc) Tìm nghiệm của H(x).",
    "choices": [],
    "answer": 0,
    "steps": [
      {
        "text": "Dựa vào kiến thức đã học để trả lời.",
        "highlight": null
      }
    ],
    "images": [],
    "type": "essay"
  },
  "g7-math-45": {
    "id": "g7-math-45",
    "topicId": "g7-math",
    "question": "Cho các đa thức\n2\n3\n3\n2\nM(x)\n4x\nx\n2x\n3\nx\nx\n3x\n2x\n\n\n\n\n\n\n\n;\n2\n3\n2\nN(x)\nx\n3\n2x\n3x\nx",
    "choices": [],
    "answer": 0,
    "steps": [
      {
        "text": "Dựa vào kiến thức đã học để trả lời.",
        "highlight": null
      }
    ],
    "images": [],
    "type": "essay"
  },
  "g7-math-46": {
    "id": "g7-math-46",
    "topicId": "g7-math",
    "question": "Cho hai đa thức\n\n\n\n4\n5\n2\n4\n5\n3\n5\n3\n5\n14\n6\n1\nM x\nx\nx\nx x\nx\nx\nx\nx\n\n\n\n\n\n\n\n\n\n\n\n\n4\n3\n5\n4\n3\n5\n3\n3\n2\n4\n3\n5\nN x\nx\nx\nx\nx\nx\nx\nx\n\n\n\n\n\n\n\n\na) Thu gọn và sắp xếp hai đa thức trên theo lũy thừa giảm dần của biến\nb) Tính\n\n\n\n\n\n\n;\nH x\nM x\nN x G x\nM x\nN x\n\n\n\n\nc) Tìm hệ số cao nhất và hệ số tự do của\n\nH x  và\n\nG x\nd) Tính\n\n\n\n\n",
    "choices": [],
    "answer": 0,
    "steps": [
      {
        "text": "Dựa vào kiến thức đã học để trả lời.",
        "highlight": null
      }
    ],
    "images": [],
    "type": "essay"
  },
  "g7-math-47": {
    "id": "g7-math-47",
    "topicId": "g7-math",
    "question": "Thực hiện các phép tính sau\na)\n4\n2\n2\n5\n.\n5\n9\nx\nx\n\n\n\n\n\n\n\n\n\n\nb)\n\n\n3\n2\n1\n.\n.\n5",
    "choices": [],
    "answer": 0,
    "steps": [
      {
        "text": "Dựa vào kiến thức đã học để trả lời.",
        "highlight": null
      }
    ],
    "images": [],
    "type": "essay"
  },
  "g7-math-48": {
    "id": "g7-math-48",
    "topicId": "g7-math",
    "question": "Tìm x  biết\na) \n\n2\n2\n1\n(3\n)\n0\n\n\n\n\nx x\nx\nx\nb) 3 (12\n4)",
    "choices": [],
    "answer": 0,
    "steps": [
      {
        "text": "Dựa vào kiến thức đã học để trả lời.",
        "highlight": null
      }
    ],
    "images": [],
    "type": "essay"
  },
  "g7-math-49": {
    "id": "g7-math-49",
    "topicId": "g7-math",
    "question": "Thực hiện các phép tính sau\na) \n\n5\n2\n3\n2\n2\n6\n4\n: 2\nx\nx\nx\nx\n\n\n\nb)\n\n\n5\n3\n2\n8\n3\n4\n:\n3\n3\nx\nx\nx\nx\n\n\n\n\n\n\n\n\n\nc) \n\n\n3\n2\n16\n2\n3",
    "choices": [],
    "answer": 0,
    "steps": [
      {
        "text": "Dựa vào kiến thức đã học để trả lời.",
        "highlight": null
      }
    ],
    "images": [],
    "type": "essay"
  },
  "g7-math-50": {
    "id": "g7-math-50",
    "topicId": "g7-math",
    "question": ":\n1\nx\nx\nx\nx\nx\nx\n\n\n\n\n\n",
    "choices": [
      "HÌNH HỌC."
    ],
    "answer": 0,
    "steps": [
      {
        "text": "Dựa vào kiến thức đã học để trả lời.",
        "highlight": null
      }
    ],
    "images": []
  },
  "g7-math-51": {
    "id": "g7-math-51",
    "topicId": "g7-math",
    "question": "Cho  ∆ABC cân tại A. Đường phân giác AM xuất phát từ đỉnh A của ∆ABC.\na) Chứng minh AMB = AMC.\nb) Chứng minh M là trung điểm của BC và AM  BC\nc) Từ M vẽ ME  AB (E thuộc AB) và MF  AC (F thuộc AC). Chứng minh AM là đường trung trực\ncủa EF.\nd) Chứng minh EF//BC\n6",
    "choices": [],
    "answer": 0,
    "steps": [
      {
        "text": "Dựa vào kiến thức đã học để trả lời.",
        "highlight": null
      }
    ],
    "images": [],
    "type": "essay"
  },
  "g7-math-52": {
    "id": "g7-math-52",
    "topicId": "g7-math",
    "question": "Cho ∆ABC cân tại A và hai đường trung tuyến BM, CN cắt nhau tại K.\na) Chứng minh BNC =  CMB\nb) Chứng minh ∆BKC cân tại K\nc) Chứng minh BC < 4.KM",
    "choices": [],
    "answer": 0,
    "steps": [
      {
        "text": "Dựa vào kiến thức đã học để trả lời.",
        "highlight": null
      }
    ],
    "images": [],
    "type": "essay"
  },
  "g7-math-53": {
    "id": "g7-math-53",
    "topicId": "g7-math",
    "question": "Cho ΔABC cân tại A. Vẽ AH vuông góc với BC tại H.\na) Chứng minh rằng ΔHAB = ΔHAC.\nb) Gọi D là điểm nằm trên đoạn thẳng AH. Trên tia đối của tia DB lấy điểm E sao cho DE = DB.\nChứng minh rằng AD + DE > AC.\nc) Gọi K là điểm trên đoạn thẳng CD sao cho\nCD\n3\n2\nCK \n. Chứng minh rằng 3 điểm H, K, E thẳng\nhàng.",
    "choices": [],
    "answer": 0,
    "steps": [
      {
        "text": "Dựa vào kiến thức đã học để trả lời.",
        "highlight": null
      }
    ],
    "images": [],
    "type": "essay"
  },
  "g7-math-54": {
    "id": "g7-math-54",
    "topicId": "g7-math",
    "question": "Cho tam giác nhọn ABC  có AB\nAC\n\n, đường cao AD. Trên đoạn DC  lấy điểm E  sao cho\nDB\nDE\n\na) Chứng minh tam giác ABE  cân\nb) Từ E  kẻ EF  vuông góc với AC (F thuộc AC ). Từ C  kẻ CK  vuông góc với AE  ( K  thuộc\n)\nAE .\nChứng minh rằng ba đường thẳng\n,\nAD EF  và CK  đồng quy tại một điểm.",
    "choices": [],
    "answer": 0,
    "steps": [
      {
        "text": "Dựa vào kiến thức đã học để trả lời.",
        "highlight": null
      }
    ],
    "images": [],
    "type": "essay"
  },
  "g7-math-55": {
    "id": "g7-math-55",
    "topicId": "g7-math",
    "question": "Cho ABC\n\nvuông tại A, đường phân giác\n(\n).\nBE E\nAC\n\nTrên cạnh BC  lấy điểm H sao cho\n,\nBH\nBA\n\ngọi giao điểm của BAvà HE là K . Chứng minh rằng :\na)  ABE\nHBE\n\n\n.\nb) BElà đường trung trực của AH .\nc) E là trực tâm của BKC\n\n.\nd) So sánh AE và EC .\ne) ABC\n\ncần có thêm điều kiện gì để điểm E cách đều ba đỉnh của\n.\nBKC\n",
    "choices": [],
    "answer": 0,
    "steps": [
      {
        "text": "Dựa vào kiến thức đã học để trả lời.",
        "highlight": null
      }
    ],
    "images": [],
    "type": "essay"
  },
  "g7-math-56": {
    "id": "g7-math-56",
    "topicId": "g7-math",
    "question": "Cho tam giác ABC cân tại ,\nA  kẻ đường cao AH. Gọi M  là trung điểm của BH. Vẽ điểm N sao\ncho M là trung điểm của AN\na) Chứng minh\n;\nAMH\nNMB NB\nBC\n\n\n\n.\nb) Chứng minh  BN < BA.\nc) Chứng minh rằng  \n.\nBAM\nMAH\n\nd) Gọi I  là trung điểm của\n.\nNC  Chứng minh rằng ba điểm\n,\n,\nA H I  thẳng hàng.",
    "choices": [],
    "answer": 0,
    "steps": [
      {
        "text": "Dựa vào kiến thức đã học để trả lời.",
        "highlight": null
      }
    ],
    "images": [],
    "type": "essay"
  },
  "g7-math-57": {
    "id": "g7-math-57",
    "topicId": "g7-math",
    "question": "Cho ΔABC vuông tại A có BE là đường trung tuyến. Trên tia đối của tia EB lấy điểm K sao cho\nEB = EK.\na) Chứng minh ΔABE = ΔCKE.\nb) Vẽ\nBE\nAM \ntại M,\nEK\nCN \ntại N. Chứng minh AM = CN.\nc) Chứng minh\nBE\n2\nBC\nAB\n\n\n.\nd) Vẽ đường cao EH của ΔBCE. Chứng minh các đường thẳng BA, HE, CN đồng quy tại một điểm.",
    "choices": [],
    "answer": 0,
    "steps": [
      {
        "text": "Dựa vào kiến thức đã học để trả lời.",
        "highlight": null
      }
    ],
    "images": [],
    "type": "essay"
  },
  "g7-math-58": {
    "id": "g7-math-58",
    "topicId": "g7-math",
    "question": "Cho tam giác ABC cân tại A, đường cao AH (H ∈ BC).\na) Chứng minh ∆AHB = ∆AHC.\nAD = DH\nc) Gọi E là trung điểm AC, CD cắt AH tại G. Chứng minh B, G, E thẳng hàng.\nd) Chứng minh: chu vi ∆ABC > AH + 3BG\n7",
    "choices": [
      "Chứng minh ∆ADH cân, từ đó suy ra"
    ],
    "answer": 0,
    "steps": [
      {
        "text": "Dựa vào kiến thức đã học để trả lời.",
        "highlight": null
      }
    ],
    "images": []
  },
  "g7-math-59": {
    "id": "g7-math-59",
    "topicId": "g7-math",
    "question": "Quan sát các hình vẽ và hoàn thành bảng sau:\nHình (1)\nHình (2)\nHình (3)\nHình (4)\nHình\n(1)\n(2)\n(3)\n(4)\nTên gọi\nSố mặt\nSố đỉnh\nSố cạnh\nMặt bên là hình\nDiện tích\nxung quanh\nThể tích",
    "choices": [],
    "answer": 0,
    "steps": [
      {
        "text": "Dựa vào kiến thức đã học để trả lời.",
        "highlight": null
      }
    ],
    "images": [
      "/images/g7_exams/img_64aeebc2.jpeg",
      "/images/g7_exams/img_fccbee20.jpeg",
      "/images/g7_exams/img_b700139e.jpeg",
      "/images/g7_exams/img_2c3a33c5.jpeg",
      "/images/g7_exams/img_647980cc.jpeg"
    ],
    "type": "essay"
  },
  "g7-math-60": {
    "id": "g7-math-60",
    "topicId": "g7-math",
    "question": "Hùng làm một con xúc xắc hình lập phương có kích thước như hình vẽ a từ tấm bìa có hình\ndạng như hình b. Em hãy tính diện tích tấm bìa và thể tích con xúc xắc.",
    "choices": [],
    "answer": 0,
    "steps": [
      {
        "text": "Dựa vào kiến thức đã học để trả lời.",
        "highlight": null
      }
    ],
    "images": [
      "/images/g7_exams/img_7c637bac.jpeg"
    ],
    "type": "essay"
  },
  "g7-math-61": {
    "id": "g7-math-61",
    "topicId": "g7-math",
    "question": "Thùng đựng bằng thép của một máy cắt cỏ có dạng lăng trụ đứng tam giác (như hình vẽ).\na) Tính dung tích của thùng.\nb) Tính diện tích thép cần để làm thùng đựng cỏ (giả sử lượng thép làm các mối nối là không đáng kể)",
    "choices": [],
    "answer": 0,
    "steps": [
      {
        "text": "Dựa vào kiến thức đã học để trả lời.",
        "highlight": null
      }
    ],
    "images": [],
    "type": "essay"
  },
  "g7-math-62": {
    "id": "g7-math-62",
    "topicId": "g7-math",
    "question": "Một căn phòng dạng hình hộp chữ nhật có chiều dài12,6 m ; chiều rộng 7,2 m; chiều cao35 m .\nNgười ta muốn lăn sơn tường và trần nhà. Hỏi diện tích cần lăn sơn là bao nhiêu mét vuông, biết rằng\ntổng diện tích các cửa bằng\n2",
    "choices": [],
    "answer": 0,
    "steps": [
      {
        "text": "Dựa vào kiến thức đã học để trả lời.",
        "highlight": null
      }
    ],
    "images": [],
    "type": "essay"
  },
  "g7-math-63": {
    "id": "g7-math-63",
    "topicId": "g7-math",
    "question": "Một chiếc bánh kem có dạng hình hộp chữ nhật với chiều dài là 25 cm , chiều rộng là 20 cm và\nchiều cao là 15 cm. Người ta cắt đi một miếng bánh có dạng hình lập phương cạnh là 3 cm . Tính thể tích\nphần còn lại của chiếc bánh kem.",
    "choices": [],
    "answer": 0,
    "steps": [
      {
        "text": "Dựa vào kiến thức đã học để trả lời.",
        "highlight": null
      }
    ],
    "images": [],
    "type": "essay"
  },
  "g7-math-64": {
    "id": "g7-math-64",
    "topicId": "g7-math",
    "question": "Một bể cá cảnh có đáy là hình vuông cạnh 50 cm, chiều cao 80 cm. Lúc đầu bể không có nước,\nngười ta đổ vào bể 150 lít nước. Hỏi mặt nước còn cách thành bể bao nhiêu cm?",
    "choices": [
      "BÀI TẬP NÂNG CAO"
    ],
    "answer": 0,
    "steps": [
      {
        "text": "Dựa vào kiến thức đã học để trả lời.",
        "highlight": null
      }
    ],
    "images": []
  },
  "g7-math-65": {
    "id": "g7-math-65",
    "topicId": "g7-math",
    "question": "Cho đa thức\n\n10\n9\n8\n7\n101\n101\n101\n..... 101\n101\nf x\nx\nx\nx\nx\nx\n\n\n\n\n\n\n\n. Tính\n\n\n100\nf\nBài 2.\na) Tìm giá trị nhỏ nhất của các biểu thức sau:\nA = x4 + 3x2 + 2           B = x2 + 4x – 100             C =  4\nx\nx\n3\n\n\n\n\nx \nb) Tìm giá trị lớn nhất của biểu thức sau:\nD = -3x2 – 5|y+1| + 3       E = - x2 – 2x + 7            F =\n\n\n2\n2020\nx\n3\ny\n1\n5\n\n\n\n",
    "choices": [],
    "answer": 0,
    "steps": [
      {
        "text": "Dựa vào kiến thức đã học để trả lời.",
        "highlight": null
      }
    ],
    "images": [],
    "type": "essay"
  },
  "g7-math-66": {
    "id": "g7-math-66",
    "topicId": "g7-math",
    "question": "Tìm nghiệm của các đa thức sau:          a) x2 + 4x +4          b)  - x2 + 5x + 6",
    "choices": [],
    "answer": 0,
    "steps": [
      {
        "text": "Dựa vào kiến thức đã học để trả lời.",
        "highlight": null
      }
    ],
    "images": [],
    "type": "essay"
  },
  "g7-math-67": {
    "id": "g7-math-67",
    "topicId": "g7-math",
    "question": "Cho đa thức P(x) = ax3 + bx2 + cx + d với a, b, c, d là các hệ số nguyên. Biết rằng P(x) chia hết\ncho 5 với mọi x là số nguyên. Chứng tỏ các số nguyên a, b, c, d cũng chia hết cho 5.",
    "choices": [],
    "answer": 0,
    "steps": [
      {
        "text": "Dựa vào kiến thức đã học để trả lời.",
        "highlight": null
      }
    ],
    "images": [],
    "type": "essay"
  },
  "g7-math-68": {
    "id": "g7-math-68",
    "topicId": "g7-math",
    "question": "Cho đa thức P(x) = ax3 + bx2 + cx + d. Tìm các hệ số a, b, c, d biết:\nP(0) = -5;  P(1) = 4;  P(2) = 31; P(3) = 88.",
    "choices": [],
    "answer": 0,
    "steps": [
      {
        "text": "Dựa vào kiến thức đã học để trả lời.",
        "highlight": null
      }
    ],
    "images": [],
    "type": "essay"
  },
  "g7-math-69": {
    "id": "g7-math-69",
    "topicId": "g7-math",
    "question": "Cho đa thức f(x) thỏa mãn điều kiện: x.f (x\n2)\n(x\n4).f (x)\n\n\n\nChứng minh rằng đa thức f(x) có ít nhất hai nghiệm.",
    "choices": [],
    "answer": 0,
    "steps": [
      {
        "text": "Dựa vào kiến thức đã học để trả lời.",
        "highlight": null
      }
    ],
    "images": [],
    "type": "essay"
  },
  "g7-math-70": {
    "id": "g7-math-70",
    "topicId": "g7-math",
    "question": "Xét đa thức\n3\n2\nP(x)\nax\nbx\ncx\nd\n\n\n\n\n. Chứng minh rằng:\na) Nếu a\nb\nc\nd\n0\n\n\n\n\nthì P(x)  có một nghiệm x\n1.\n\nb) Nếu a\nb\nc\nd\n0\n\n\n\n\nthì P(x) có một nghiệm x\n1.\n",
    "choices": [],
    "answer": 0,
    "steps": [
      {
        "text": "Dựa vào kiến thức đã học để trả lời.",
        "highlight": null
      }
    ],
    "images": [],
    "type": "essay"
  },
  "g7-math-71": {
    "id": "g7-math-71",
    "topicId": "g7-math",
    "question": "Cho đa thức\n2\n( ) \n\n\nA x\nax\nbx\nc (a, b, c là các hệ số; x  là biến).\na) Hãy tính\n( 1)\n\nA\n, biết a - b = 12 - c.\nb) Tìm a, b, c biết\n(0)\n1; (1)\n0; (2)\n5\nA\nA\nA\n\n\n\nc) Biết 8\n2\n0\n\n\na\nc\n. Chứng tỏ rằng:\n(2). ( 2)\n0\n\n\nA\nA\n.............................................................Hết......................................................",
    "choices": [],
    "answer": 0,
    "steps": [
      {
        "text": "Dựa vào kiến thức đã học để trả lời.",
        "highlight": null
      }
    ],
    "images": [],
    "type": "essay"
  }
}